Workbook
Name _4_FINAL_PERMITS_34_T: Dataset!$A$1:$X$4145

Sheet Dataset
A1: PTO_RECORD_ID | B1: PTO_STATUS | C1: OPEN_DATE | D1: EQUIPMENT_TYPE | E1: DBA | F1: PTO_CONTACT | G1: EQUIP_LOCATION_ADDRESS | H1: ZIP_CODE | I1: SECTOR | J1: PERMIT_DESCRIPTION | K1: Diesel | L1: Petroleum | M1: Natural Gas | N1: Propane | O1: Sum | P1: Fuel | Q1: Capacity listed (kW) | R1: Horsepower | S1: Total Capacity (kW) | T1: FIRST_READING_DT | U1: FIRST_READING_OF_YEAR | V1: LAST_READING_DT | W1: LAST_READING_OF_YEAR | X1: LAST READING - FIRST READING | Y1: Electricity Generation (kWh) | Z1: Estimated Emissions (tCO2) | AA1: Latitude | AB1: Longitude | AC1: Accuracy Score | AD1: Accuracy Type | AE1: Number | AF1: Street | AG1: Unit Type | AH1: Unit Number | AI1: City | AJ1: State | AK1: County | AL1: Zip | AM1: Country | AN1: Source
A2: APCD1995-PTO-890540 | B2: Active | C2: 40025 | D2: [34C] Emergency Standby Engine | E2: EMERALD PLAZA | G2: 402 BROADWAY W SAN DIEGO, CA | H2: 92101 | I2: N | J2: EMERGENCY GENERATOR: (1) KOHLER MODEL, 750 KW, DRIVEN BY A DETROIT DIESEL ENGINE, MODEL # 816317416, V-16, S/N 7A00049, ENGINE # 16vf008489, TURBOCHARGED, 1232 BHP (UNIT #FOO8489) 17CCR93115 SJE 11/05 (ATCM DATA: S/N 7A00049) | K2: =IFERROR(IF(SEARCH(K$1,$J2)>0,1),0) -> 1 | L2: =IFERROR(IF(SEARCH(L$1,$J2)>0,1),0) -> 0 | M2: =IFERROR(IF(SEARCH(M$1,$J2)>0,1),0) -> 0 | N2: =IFERROR(IF(SEARCH(N$1,$J2)>0,1),0) -> 0 | O2: =SUM(K2:N2) -> 1 | P2: Diesel | Q2: 750 | R2: 1232 | S2: =IFERROR(IF(ISBLANK(Q2)=FALSE,Q2,R2*0.7457),"Unknown") -> 750 | T2: 44497 | U2: 431.70 | V2: 44791 | W2: 445.20 | X2: 13.5 | Y2: =X2*S2 -> 10125 | Z2: =IFERROR(INDEX(EFs!B:B,MATCH(P2,EFs!A:A,0))*Dataset!Y2/1000,0) -> 9.1974783 | AA2: 32.715933 | AB2: -117.16084 | AC2: 1 | AD2: rooftop | AE2: 402 | AF2: Broadway | AI2: San Diego | AJ2: CA | AK2: San Diego County | AL2: 92101 | AM2: US | AN2: San Diego Geographic Information Source - JPA
A3: APCD1998-PTO-960036 | B3: Active | C3: 40025 | D3: [34W] Registered Engine (Rule 12) | E3: Ramona Municipal Water District | F3: Facility Manager | G3: 260 Sawday St Ramona, CA | H3: 92065 | I3: F | J3: EMERGENCY STANDBY ENGINE: INTERNATIONAL-HARVESTER ENGINE, MODEL V-549,S/N 145136850KR-15R, 172 BHP, PROPANE-FIRED, DRIVING AN ONAN GENERATOR. (960036-CCN-2/98) | K3: =IFERROR(IF(SEARCH(K$1,$J3)>0,1),0) -> 0 | L3: =IFERROR(IF(SEARCH(L$1,$J3)>0,1),0) -> 0 | M3: =IFERROR(IF(SEARCH(M$1,$J3)>0,1),0) -> 0 | N3: =IFERROR(IF(SEARCH(N$1,$J3)>0,1),0) -> 1 | O3: =SUM(K3:N3) -> 1 | P3: Propane | R3: 172 | S3: =IFERROR(IF(Q3<>"",Q3,R3*0.7457),"Unknown") -> 128.2604 | T3: 44532 | U3: 747.80 | V3: 44532 | W3: 754.20 | X3: 6.4 | Y3: =X3*S3 -> 820.86656 | Z3: =IFERROR(INDEX(EFs!B:B,MATCH(P3,EFs!A:A,0))*Dataset!Y3/1000,0) -> 0.67631196 | AA3: 33.029999 | AB3: -116.9007 | AC3: 1 | AD3: range_interpolation | AE3: 260 | AF3: Sawday St | AI3: Ramona | AJ3: CA | AK3: San Diego County | AL3: 92065 | AM3: US | AN3: TIGER/LineÂ® dataset from the US Census Bureau
A4: APCD1998-PTO-960492 | B4: Active | C4: 40025 | D4: [34W] Registered Engine (Rule 12) | E4: UCSD Elliot Field | F4: Valerie Fanning | G4: 10205 Pomerado Road San Diego, CA | H4: 92131 | I4: F | J4: Registration of Stationary Emergency Stand-by Engine_x000D_IHC, Model: UV549, S/N: V-549-3960KOCLQ1, 100 hp, Fuel: Natural Gas_x000D_Year operated in San Diego County: 1997 _x000D_APCD2009-CER-000077/SH 16-Feb-2010 | K4: =IFERROR(IF(SEARCH(K$1,$J4)>0,1),0) -> 0 | L4: =IFERROR(IF(SEARCH(L$1,$J4)>0,1),0) -> 0 | M4: =IFERROR(IF(SEARCH(M$1,$J4)>0,1),0) -> 1 | N4: =IFERROR(IF(SEARCH(N$1,$J4)>0,1),0) -> 0 | O4: =SUM(K4:N4) -> 1 | P4: Natural Gas | R4: 100 | S4: =IFERROR(IF(Q4<>"",Q4,R4*0.7457),"Unknown") -> 74.57 | T4: 44376 | U4: 950.40 | V4: 44764 | W4: 950.40 | X4: 0 | Y4: =X4*S4 -> 0 | Z4: =IFERROR(INDEX(EFs!B:B,MATCH(P4,EFs!A:A,0))*Dataset!Y4/1000,0) -> 0 | AA4: 32.895794 | AB4: -117.1072 | AC4: 1 | AD4: range_interpolation | AE4: 10205 | AF4: Pomerado Rd | AI4: San Diego | AJ4: CA | AK4: San Diego County | AL4: 92131 | AM4: US | AN4: TIGER/LineÂ® dataset from the US Census Bureau
A5: APCD1998-PTO-961717 | B5: Active | C5: 40025 | D5: [34W] Registered Engine (Rule 12) | E5: Sea World San Diego | F5: Steve Melanese | G5: 500 Sea World Dr San Diego, CA | H5: 92109 | I5: I | J5: EMERGENCY STANDBY ENGINE: GENERAC MODEL 74GN, S/N 2029404, 160 BHP, NATURAL GAS FUELED. (961717-CCN-3/98) | K5: =IFERROR(IF(SEARCH(K$1,$J5)>0,1),0) -> 0 | L5: =IFERROR(IF(SEARCH(L$1,$J5)>0,1),0) -> 0 | M5: =IFERROR(IF(SEARCH(M$1,$J5)>0,1),0) -> 1 | N5: =IFERROR(IF(SEARCH(N$1,$J5)>0,1),0) -> 0 | O5: =SUM(K5:N5) -> 1 | P5: Natural Gas | R5: 160 | S5: =IFERROR(IF(Q5<>"",Q5,R5*0.7457),"Unknown") -> 119.312 | Y5: =X5*S5 -> 0 | Z5: =IFERROR(INDEX(EFs!B:B,MATCH(P5,EFs!A:A,0))*Dataset!Y5/1000,0) -> 0 | AA5: 32.761102 | AB5: -117.22194 | AC5: 1 | AD5: range_interpolation | AE5: 500 | AF5: Sea World Dr | AI5: San Diego | AJ5: CA | AK5: San Diego County | AL5: 92109 | AM5: US | AN5: TIGER/LineÂ® dataset from the US Census Bureau
A6: APCD1999-PTO-972305 | B6: Active | C6: 40025 | D6: [34W] Registered Engine (Rule 12) | E6: USN FASOTRAGRUPAC | F6: Commanding Officer | G6: 34567 Hwy 79 South Warner Springs, CA | H6: 92086 | I6: B | J6: EMERGENCY ENGINE GENERATOR: 207 HORSEPOWER CUMMINS MODEL G855 PROPANE ENGINE SERIAL NUMBER 25192953. 972305 GDS 2/99 | K6: =IFERROR(IF(SEARCH(K$1,$J6)>0,1),0) -> 0 | L6: =IFERROR(IF(SEARCH(L$1,$J6)>0,1),0) -> 0 | M6: =IFERROR(IF(SEARCH(M$1,$J6)>0,1),0) -> 0 | N6: =IFERROR(IF(SEARCH(N$1,$J6)>0,1),0) -> 1 | O6: =SUM(K6:N6) -> 1 | P6: Propane | R6: 207 | S6: =IFERROR(IF(Q6<>"",Q6,R6*0.7457),"Unknown") -> 154.3599 | T6: 44404 | U6: 846.20 | V6: 44739 | W6: 949.20 | X6: 103 | Y6: =X6*S6 -> 15899.07 | Z6: =IFERROR(INDEX(EFs!B:B,MATCH(P6,EFs!A:A,0))*Dataset!Y6/1000,0) -> 13.099244 | AA6: 33.338921 | AB6: -116.71941 | AC6: 1 | AD6: range_interpolation | AE6: 34567 | AF6: Hwy 79 | AI6: Warner Springs | AJ6: CA | AK6: San Diego County | AL6: 92086 | AM6: US | AN6: TIGER/LineÂ® dataset from the US Census Bureau
A7: APCD2000-PTO-961607 | B7: Active | C7: 40025 | D7: [34W] Registered Engine (Rule 12) | E7: San Diego State University | F7: Lilly Sabet | G7: 5500 Campanile Dr San Diego, CA | H7: 92182 | I7: K | J7: EMERGENCY STANDBY ENGINE: FORD MODEL CSG-6491, S/N 25043-616KR, 82 BHP, NATURAL GAS FUELED, LOCATED AT THE LOVE LIBRARY. (961606-CCN-3/98) | K7: =IFERROR(IF(SEARCH(K$1,$J7)>0,1),0) -> 0 | L7: =IFERROR(IF(SEARCH(L$1,$J7)>0,1),0) -> 0 | M7: =IFERROR(IF(SEARCH(M$1,$J7)>0,1),0) -> 1 | N7: =IFERROR(IF(SEARCH(N$1,$J7)>0,1),0) -> 0 | O7: =SUM(K7:N7) -> 1 | P7: Natural Gas | R7: 82 | S7: =IFERROR(IF(Q7<>"",Q7,R7*0.7457),"Unknown") -> 61.1474 | T7: 44490 | U7: 2850.00 | V7: 44490 | W7: 2855.20 | X7: 5.2 | Y7: =X7*S7 -> 317.96648 | Z7: =IFERROR(INDEX(EFs!B:B,MATCH(P7,EFs!A:A,0))*Dataset!Y7/1000,0) -> 0.23092497 | AA7: 32.772147 | AB7: -117.07255 | AC7: 1 | AD7: rooftop | AE7: 5500 | AF7: Campanile Dr | AI7: San Diego | AJ7: CA | AK7: San Diego County | AL7: 92182 | AM7: US | AN7: San Diego Geographic Information Source - JPA
A8: APCD2000-PTO-961608 | B8: Active | C8: 40025 | D8: [34W] Registered Engine (Rule 12) | E8: San Diego State University | F8: Lilly Sabet | G8: 5500 Campanile Dr San Diego, CA | H8: 92182 | I8: K | J8: EMERGENCY STANDBY ENGINE: FORD MODEL CSG-6491, 82 BHP, NATURAL GAS FUELED, LOCATED IN THE NEW ART BUILDING. S/N 13670. (961608-CCN-3/98) | K8: =IFERROR(IF(SEARCH(K$1,$J8)>0,1),0) -> 0 | L8: =IFERROR(IF(SEARCH(L$1,$J8)>0,1),0) -> 0 | M8: =IFERROR(IF(SEARCH(M$1,$J8)>0,1),0) -> 1 | N8: =IFERROR(IF(SEARCH(N$1,$J8)>0,1),0) -> 0 | O8: =SUM(K8:N8) -> 1 | P8: Natural Gas | R8: 82 | S8: =IFERROR(IF(Q8<>"",Q8,R8*0.7457),"Unknown") -> 61.1474 | T8: 44490 | U8: 3562.90 | V8: 44490 | W8: 3568.20 | X8: 5.3 | Y8: =X8*S8 -> 324.08122 | Z8: =IFERROR(INDEX(EFs!B:B,MATCH(P8,EFs!A:A,0))*Dataset!Y8/1000,0) -> 0.23536584 | AA8: 32.772147 | AB8: -117.07255 | AC8: 1 | AD8: rooftop | AE8: 5500 | AF8: Campanile Dr | AI8: San Diego | AJ8: CA | AK8: San Diego County | AL8: 92182 | AM8: US | AN8: San Diego Geographic Information Source - JPA
A9: APCD2001-PTO-961873 | B9: Active | C9: 40025 | D9: [34W] Registered Engine (Rule 12) | E9: Fairbanks Ranch Community SVC DIST | F9: General Manager | G9: 16556 Circa del Norte Rancho Santa Fe, CA | H9: 92067 | I9: E | J9: EMERGENCY ENGINE GENERATOR, 102 HP JOHN DEERE DIESEL ENGINE, MODEL 4039-TF, S/N CD 4039T186943, TURBOCHARGED, APPL# 961873 EFH 05/99 | K9: =IFERROR(IF(SEARCH(K$1,$J9)>0,1),0) -> 1 | L9: =IFERROR(IF(SEARCH(L$1,$J9)>0,1),0) -> 0 | M9: =IFERROR(IF(SEARCH(M$1,$J9)>0,1),0) -> 0 | N9: =IFERROR(IF(SEARCH(N$1,$J9)>0,1),0) -> 0 | O9: =SUM(K9:N9) -> 1 | P9: Diesel | R9: 102 | S9: =IFERROR(IF(Q9<>"",Q9,R9*0.7457),"Unknown") -> 76.0614 | T9: 44562 | U9: 214.30 | V9: 44562 | W9: 224.90 | X9: 10.6 | Y9: =X9*S9 -> 806.25084 | Z9: =IFERROR(INDEX(EFs!B:B,MATCH(P9,EFs!A:A,0))*Dataset!Y9/1000,0) -> 0.73239256 | AA9: 32.998916 | AB9: -117.1908 | AC9: 1 | AD9: rooftop | AE9: 16556 | AF9: Circa Del Norte | AI9: Rancho Santa Fe | AJ9: CA | AK9: San Diego County | AL9: 92067 | AM9: US | AN9: San Diego Geographic Information Source - JPA
A10: APCD2002-PTO-940514 | B10: Active | C10: 40025 | D10: [34C] Emergency Standby Engine | E10: Sweetwater Authority Water District | F10: Plant Maint Super | G10: 3066 N Second Av Chula Vista, CA | H10: 91910 | I10: Q | J10: EMERGENCY ENGINE GENERATOR SET: CUMMINS ENGINE, PROPANE GAS FIRED, MODEL WSG-1068, RATED AT 131.6 BHP, MODEL YEAR 2012, S/N 121150134, EPA ENGINE FAMILY NUMBER: CCEXB06.8GDB , WITH AN AIR FUEL RATIO CONTROLLER AND A THREE-WAY CATALYST CLOSED LOOP SYSTEM, ENGINE POWERS A 85 KW GENERATOR. | K10: =IFERROR(IF(SEARCH(K$1,$J10)>0,1),0) -> 0 | L10: =IFERROR(IF(SEARCH(L$1,$J10)>0,1),0) -> 0 | M10: =IFERROR(IF(SEARCH(M$1,$J10)>0,1),0) -> 0 | N10: =IFERROR(IF(SEARCH(N$1,$J10)>0,1),0) -> 1 | O10: =SUM(K10:N10) -> 1 | P10: Propane | Q10: 85 | R10: 131.6 | S10: =IFERROR(IF(Q10<>"",Q10,R10*0.7457),"Unknown") -> 85 | T10: 44491 | U10: 50.20 | V10: 44491 | W10: 52.40 | X10: 2.2 | Y10: =X10*S10 -> 187 | Z10: =IFERROR(INDEX(EFs!B:B,MATCH(P10,EFs!A:A,0))*Dataset!Y10/1000,0) -> 0.1540693 | AA10: 32.65953 | AB10: -117.08502 | AC10: 1 | AD10: rooftop | AE10: 3066 | AF10: N 2nd Ave | AI10: Chula Vista | AJ10: CA | AK10: San Diego County | AL10: 91910 | AM10: US | AN10: Sandoval
A11: APCD2002-PTO-960515 | B11: Active | C11: 40025 | D11: [34W] Registered Engine (Rule 12) | E11: Fleet Readiness Center Southwest | G11: NAS North Island San Diego, CA | H11: 92135 | I11: O | J11: EMERGENCY STANDBY ENGINE, CHRYSLER MODEL LH-318; S/N E-574874; 187 BHP, NATURAL GAS FIRED. APPL 960515 EFH 09/98 REVISION DATE 6-1-02 | K11: =IFERROR(IF(SEARCH(K$1,$J11)>0,1),0) -> 0 | L11: =IFERROR(IF(SEARCH(L$1,$J11)>0,1),0) -> 0 | M11: =IFERROR(IF(SEARCH(M$1,$J11)>0,1),0) -> 1 | N11: =IFERROR(IF(SEARCH(N$1,$J11)>0,1),0) -> 0 | O11: =SUM(K11:N11) -> 1 | P11: Natural Gas | R11: 187 | S11: =IFERROR(IF(Q11<>"",Q11,R11*0.7457),"Unknown") -> 139.4459 | Y11: =X11*S11 -> 0 | Z11: =IFERROR(INDEX(EFs!B:B,MATCH(P11,EFs!A:A,0))*Dataset!Y11/1000,0) -> 0 | AA11: 33.232765 | AB11: -117.35203 | AC11: 0.8 | AD11: street_center | AF11: New Branch Ct | AI11: Oceanside | AJ11: CA | AK11: San Diego County | AL11: 92058 | AM11: US | AN11: TIGER/LineÂ® dataset from the US Census Bureau
A12: APCD2002-PTO-975748 | B12: Active | C12: 40025 | D12: [34W] Registered Engine (Rule 12) | E12: Rancho Calevero Mobile Home Park | F12: General Manager | G12: 3527 Calevero Ln Oceanside, CA | H12: 92056 | I12: C | J12: FORD NATURAL GAS ENGINE, MODEL LSG-875, S/N 2202610498, 132 HP. _x000D_975748AFS22NOV2000 | K12: =IFERROR(IF(SEARCH(K$1,$J12)>0,1),0) -> 0 | L12: =IFERROR(IF(SEARCH(L$1,$J12)>0,1),0) -> 0 | M12: =IFERROR(IF(SEARCH(M$1,$J12)>0,1),0) -> 1 | N12: =IFERROR(IF(SEARCH(N$1,$J12)>0,1),0) -> 0 | O12: =SUM(K12:N12) -> 1 | P12: Natural Gas | R12: 132 | S12: =IFERROR(IF(Q12<>"",Q12,R12*0.7457),"Unknown") -> 98.4324 | T12: 44504 | U12: 66.10 | V12: 44504 | W12: 82.20 | X12: 16.1 | Y12: =X12*S12 -> 1584.7616 | Z12: =IFERROR(INDEX(EFs!B:B,MATCH(P12,EFs!A:A,0))*Dataset!Y12/1000,0) -> 1.1509422 | AA12: 33.17894 | AB12: -117.27982 | AC12: 1 | AD12: range_interpolation | AE12: 3527 | AF12: Calevero Ln | AI12: Oceanside | AJ12: CA | AK12: San Diego County | AL12: 92056 | AM12: US | AN12: TIGER/LineÂ® dataset from the US Census Bureau
A13: APCD2002-PTO-975755 | B13: Active | C13: 40025 | D13: [34W] Registered Engine (Rule 12) | E13: Clear Channel Communications | F13: Attn: Engineering | G13: 9660 Granite Ridge Dr San Diego, CA | H13: 92123 | I13: J | J13: EMERGENCY ENGINE GENERATOR, 755 HP, CUMMINS ENGINE, MODEL KTA19-G4, S/N 37195425, DRIVING ONAN CORPORATION GENERATOR, MODEL 500DFED, S/N J000164625. _x000D_APPL# 975755 EFH 04/01 (17CCR93115) SJE 10/05 | K13: =IFERROR(IF(SEARCH(K$1,$J13)>0,1),0) -> 0 | L13: =IFERROR(IF(SEARCH(L$1,$J13)>0,1),0) -> 0 | M13: =IFERROR(IF(SEARCH(M$1,$J13)>0,1),0) -> 0 | N13: =IFERROR(IF(SEARCH(N$1,$J13)>0,1),0) -> 0 | O13: =SUM(K13:N13) -> 0 | P13: Unknown | R13: 755 | S13: =IFERROR(IF(Q13<>"",Q13,R13*0.7457),"Unknown") -> 563.0035 | T13: 44562 | U13: 128.80 | V13: 44562 | W13: 137.40 | X13: 8.6 | Y13: =X13*S13 -> 4841.8301 | Z13: =IFERROR(INDEX(EFs!B:B,MATCH(P13,EFs!A:A,0))*Dataset!Y13/1000,0) -> 0 | AA13: 32.806873 | AB13: -117.12092 | AC13: 1 | AD13: rooftop | AE13: 9660 | AF13: Granite Ridge Dr | AI13: San Diego | AJ13: CA | AK13: San Diego County | AL13: 92123 | AM13: US | AN13: San Diego Geographic Information Source - JPA
A14: APCD2002-PTO-975914 | B14: Active | C14: 40025 | D14: [34W] Registered Engine (Rule 12) | E14: Dixieline Lumber Co | F14: Dennis McComb | G14: 3250 Sports Arena Blvd. San Diego, CA | H14: 92110 | I14: I | J14: EMERGENCY ENGINE: FORD, MODEL CSG 649I6005F, NATURAL GAS FIRED, 82 BHP, S/N 263731-0498, DRIVING AN ELECTRIC GENERATOR. (975914 ALC 01/01) | K14: =IFERROR(IF(SEARCH(K$1,$J14)>0,1),0) -> 0 | L14: =IFERROR(IF(SEARCH(L$1,$J14)>0,1),0) -> 0 | M14: =IFERROR(IF(SEARCH(M$1,$J14)>0,1),0) -> 1 | N14: =IFERROR(IF(SEARCH(N$1,$J14)>0,1),0) -> 0 | O14: =SUM(K14:N14) -> 1 | P14: Natural Gas | R14: 82 | S14: =IFERROR(IF(Q14<>"",Q14,R14*0.7457),"Unknown") -> 61.1474 | T14: 44558 | U14: 844.00 | V14: 44558 | W14: 875.60 | X14: 31.6 | Y14: =X14*S14 -> 1932.2578 | Z14: =IFERROR(INDEX(EFs!B:B,MATCH(P14,EFs!A:A,0))*Dataset!Y14/1000,0) -> 1.4033133 | AA14: 32.753524 | AB14: -117.2084 | AC14: 1 | AD14: rooftop | AE14: 3250 | AF14: Sports Arena Blvd | AI14: San Diego | AJ14: CA | AK14: San Diego County | AL14: 92110 | AM14: US | AN14: San Diego Geographic Information Source - JPA
A15: APCD2002-PTO-976373 | B15: Active | C15: 40025 | D15: [34W] Registered Engine (Rule 12) | E15: SD City Of Metro Wastewater Dept | G15: 3001 Ingraham ST San Diego, CA | H15: 92109 | I15: I | J15: INTERNAL COMBUSTION ENGINE. MAKE: HERCULES, MODEL: G2300. SERIAL NR.: IA3335652 G2300X210. HP RATING= 60, NATURAL GAS FUELED. SERVES AS AN EMERGENCY POWER SUPPLY. | K15: =IFERROR(IF(SEARCH(K$1,$J15)>0,1),0) -> 0 | L15: =IFERROR(IF(SEARCH(L$1,$J15)>0,1),0) -> 0 | M15: =IFERROR(IF(SEARCH(M$1,$J15)>0,1),0) -> 1 | N15: =IFERROR(IF(SEARCH(N$1,$J15)>0,1),0) -> 0 | O15: =SUM(K15:N15) -> 1 | P15: Natural Gas | R15: 60 | S15: =IFERROR(IF(Q15<>"",Q15,R15*0.7457),"Unknown") -> 44.742 | Y15: =X15*S15 -> 0 | Z15: =IFERROR(INDEX(EFs!B:B,MATCH(P15,EFs!A:A,0))*Dataset!Y15/1000,0) -> 0 | AA15: 32.773314 | AB15: -117.2347 | AC15: 1 | AD15: range_interpolation | AE15: 3001 | AF15: Ingraham St | AI15: San Diego | AJ15: CA | AK15: San Diego County | AL15: 92109 | AM15: US | AN15: TIGER/LineÂ® dataset from the US Census Bureau
A16: APCD2002-PTO-977230 | B16: Active | C16: 40025 | D16: [34C] Emergency Standby Engine | E16: San Diego State University | F16: Lilly Sabet | G16: 5500 Campanile Dr San Diego, CA | H16: 92182 | I16: K | J16: EMERGENCY STANDBY ENGINE: GENERAL MOTORS ENGINE, FUELED WITH NATURAL GAS, MODEL INDUSTRIAL POWER TRAIN, S/N 05882, 162 BHP, EQUIPPED WITH THREE-WAY CATALYTIC CONVERTER BANDITO MODEL CX-8-6, DRIVING A 121 KW GENERATOR, (977230-CCN-4/02) LOCATED AT TENOCHCA HALL. | K16: =IFERROR(IF(SEARCH(K$1,$J16)>0,1),0) -> 0 | L16: =IFERROR(IF(SEARCH(L$1,$J16)>0,1),0) -> 0 | M16: =IFERROR(IF(SEARCH(M$1,$J16)>0,1),0) -> 1 | N16: =IFERROR(IF(SEARCH(N$1,$J16)>0,1),0) -> 0 | O16: =SUM(K16:N16) -> 1 | P16: Natural Gas | Q16: 121 | R16: 162 | S16: =IFERROR(IF(Q16<>"",Q16,R16*0.7457),"Unknown") -> 121 | T16: 44495 | U16: 553.60 | V16: 44495 | W16: 558.70 | X16: 5.1 | Y16: =X16*S16 -> 617.1 | Z16: =IFERROR(INDEX(EFs!B:B,MATCH(P16,EFs!A:A,0))*Dataset!Y16/1000,0) -> 0.4481724 | AA16: 32.772147 | AB16: -117.07255 | AC16: 1 | AD16: rooftop | AE16: 5500 | AF16: Campanile Dr | AI16: San Diego | AJ16: CA | AK16: San Diego County | AL16: 92182 | AM16: US | AN16: San Diego Geographic Information Source - JPA
A17: APCD2002-PTO-977306 | B17: Active | C17: 40025 | D17: [34W] Registered Engine (Rule 12) | E17: Target Store T1040 | F17: General Manager | G17: 1751 University Dr Vista, CA | H17: 92083 | I17: C | J17: INTERNAL COMBUSTION ENGINE. MAKE: FORD; MODEL: CSG-6491-6005A. SERIAL NR.: 15408 H-08-RX. HP RATING=53. MANUFACTURE YEAR: AUGUST 1996. ENGINE OPERATES WITH NATURAL GAS WITH PROPANE AS BACK UP. EMERGENCY STANDBY POWER 35 KW GENERATION UNIT. | K17: =IFERROR(IF(SEARCH(K$1,$J17)>0,1),0) -> 0 | L17: =IFERROR(IF(SEARCH(L$1,$J17)>0,1),0) -> 0 | M17: =IFERROR(IF(SEARCH(M$1,$J17)>0,1),0) -> 1 | N17: =IFERROR(IF(SEARCH(N$1,$J17)>0,1),0) -> 1 | O17: =SUM(K17:N17) -> 2 | P17: Natural Gas | Q17: 35 | R17: 53 | S17: =IFERROR(IF(Q17<>"",Q17,R17*0.7457),"Unknown") -> 35 | T17: 44426 | U17: 242.70 | V17: 44426 | W17: 248.30 | X17: 5.6 | Y17: =X17*S17 -> 196 | Z17: =IFERROR(INDEX(EFs!B:B,MATCH(P17,EFs!A:A,0))*Dataset!Y17/1000,0) -> 0.14234612 | AA17: 33.169267 | AB17: -117.21487 | AC17: 1 | AD17: rooftop | AE17: 1751 | AF17: University Dr | AI17: Vista | AJ17: CA | AK17: San Diego County | AL17: 92083 | AM17: US | AN17: San Diego Geographic Information Source - JPA
A18: APCD2002-PTO-978134 | B18: Active | C18: 40025 | D18: [34C] Emergency Standby Engine | E18: SD CO OF DPW WASTEWATER MGMT DIV | F18: PLANT OPERATOR | G18: 215 BRIDLE RUN CT ALPINE, CA | H18: 91901 | I18: H | J18: EMERGENCY STANDBY ENGINE: GENERAL MOTORS MODEL VORTEC 8.1L, 150 HP, NATURAL GAS FIRED, ENGINE S/N 8.1L-05682, YEAR OF MANUFACTURE 2001; GENERATOR S/N 0720529, 80 KW. 978134AFS31OCT2002 | K18: =IFERROR(IF(SEARCH(K$1,$J18)>0,1),0) -> 0 | L18: =IFERROR(IF(SEARCH(L$1,$J18)>0,1),0) -> 0 | M18: =IFERROR(IF(SEARCH(M$1,$J18)>0,1),0) -> 1 | N18: =IFERROR(IF(SEARCH(N$1,$J18)>0,1),0) -> 0 | O18: =SUM(K18:N18) -> 1 | P18: Natural Gas | Q18: 80 | R18: 150 | S18: =IFERROR(IF(Q18<>"",Q18,R18*0.7457),"Unknown") -> 80 | T18: 44562 | U18: 303.70 | V18: 44562 | W18: 304.60 | X18: 0.9 | Y18: =X18*S18 -> 72 | Z18: =IFERROR(INDEX(EFs!B:B,MATCH(P18,EFs!A:A,0))*Dataset!Y18/1000,0) -> 0.052290412 | AA18: 32.833802 | AB18: -116.81834 | AC18: 1 | AD18: rooftop | AE18: 215 | AF18: Bridle Run Ct | AI18: Alpine | AJ18: CA | AK18: San Diego County | AL18: 91901 | AM18: US | AN18: Sandoval
A19: APCD2002-PTO-978485 | B19: Active | C19: 40025 | D19: [34C] Emergency Standby Engine | E19: Albertsons #3797 | F19: Jill Washburn | G19: 1601 S Melrose Dr Vista, CA | H19: 92081 | I19: B | J19: EMERGENCY ENGINE: GENERAL MOTORS, MODEL VORTEC 4.3LG, 75 BHP, NATURAL GAS FIRED, S/N 715085, DRIVING A 45-KW KOHLER MODEL 30RZG ELECTRIC GENERATOR. (978485 ALC 09/02) | K19: =IFERROR(IF(SEARCH(K$1,$J19)>0,1),0) -> 0 | L19: =IFERROR(IF(SEARCH(L$1,$J19)>0,1),0) -> 0 | M19: =IFERROR(IF(SEARCH(M$1,$J19)>0,1),0) -> 1 | N19: =IFERROR(IF(SEARCH(N$1,$J19)>0,1),0) -> 0 | O19: =SUM(K19:N19) -> 1 | P19: Natural Gas | Q19: 45 | R19: 75 | S19: =IFERROR(IF(Q19<>"",Q19,R19*0.7457),"Unknown") -> 45 | T19: 44540 | U19: 370.10 | V19: 44540 | W19: 387.20 | X19: 17.1 | Y19: =X19*S19 -> 769.5 | Z19: =IFERROR(INDEX(EFs!B:B,MATCH(P19,EFs!A:A,0))*Dataset!Y19/1000,0) -> 0.55885378 | AA19: 33.165545 | AB19: -117.24744 | AC19: 1 | AD19: rooftop | AE19: 1601 | AF19: S Melrose Dr S | AI19: Vista | AJ19: CA | AK19: San Diego County | AL19: 92081 | AM19: US | AN19: San Diego Geographic Information Source - JPA
A20: APCD2002-PTO-978614 | B20: Active | C20: 40025 | D20: [34C] Emergency Standby Engine | E20: City of Escondido - LS#05 | G20: 735 Opper Street Escondido, CA | H20: 92029 | I20: D | J20: EMERGENCY STANDBY ENGINE: GENERAL MOTORS MODEL 4.3L, 72 HP, LIQUID PROPANE FIRED, S/N 4.3L-14384, 35 KW GENERATOR. | K20: =IFERROR(IF(SEARCH(K$1,$J20)>0,1),0) -> 0 | L20: =IFERROR(IF(SEARCH(L$1,$J20)>0,1),0) -> 0 | M20: =IFERROR(IF(SEARCH(M$1,$J20)>0,1),0) -> 0 | N20: =IFERROR(IF(SEARCH(N$1,$J20)>0,1),0) -> 1 | O20: =SUM(K20:N20) -> 1 | P20: Propane | Q20: 35 | R20: 72 | S20: =IFERROR(IF(Q20<>"",Q20,R20*0.7457),"Unknown") -> 35 | T20: 44393 | U20: 411.10 | V20: 44393 | W20: 416.80 | X20: 5.7 | Y20: =X20*S20 -> 199.5 | Z20: =IFERROR(INDEX(EFs!B:B,MATCH(P20,EFs!A:A,0))*Dataset!Y20/1000,0) -> 0.16436805 | AA20: 33.131152 | AB20: -117.12637 | AC20: 1 | AD20: range_interpolation | AE20: 735 | AF20: Opper St | AI20: Escondido | AJ20: CA | AK20: San Diego County | AL20: 92029 | AM20: US | AN20: TIGER/LineÂ® dataset from the US Census Bureau
A21: APCD2003-PTO-971023 | B21: Active | C21: 40025 | D21: [34W] Registered Engine (Rule 12) | E21: USMC Base Navy Sea Ops | F21: Air Quality Section | G21: Building 31930 Camp Pendleton, CA | H21: 92055 | I21: A | J21: EMERGENCY ENGINE: FORD MODEL CSG-6491-6005-F, PROPANE FIRED, 82 HP, S/N 23887 E-11-RH, DRIVING AN ELECTRIC GENERATOR, LOCATED IN BLDG #31930 | K21: =IFERROR(IF(SEARCH(K$1,$J21)>0,1),0) -> 0 | L21: =IFERROR(IF(SEARCH(L$1,$J21)>0,1),0) -> 0 | M21: =IFERROR(IF(SEARCH(M$1,$J21)>0,1),0) -> 0 | N21: =IFERROR(IF(SEARCH(N$1,$J21)>0,1),0) -> 1 | O21: =SUM(K21:N21) -> 1 | P21: Propane | R21: 82 | S21: =IFERROR(IF(Q21<>"",Q21,R21*0.7457),"Unknown") -> 61.1474 | Y21: =X21*S21 -> 0 | Z21: =IFERROR(INDEX(EFs!B:B,MATCH(P21,EFs!A:A,0))*Dataset!Y21/1000,0) -> 0 | AA21: 33.387723 | AB21: -117.44476 | AC21: 0.5 | AD21: place | AI21: Camp Pendleton | AJ21: CA | AK21: San Diego County | AL21: 92055 | AM21: US | AN21: TIGER/LineÂ® dataset from the US Census Bureau
A22: APCD2003-PTO-971067 | B22: Active | C22: 40025 | D22: [34W] Registered Engine (Rule 12) | E22: USMC Base Marine Group Ops | F22: Air Quality Section | G22: Building 1133 Camp Pendleton, CA | H22: 92055 | I22: A | J22: EMERGENCY STANDBY ENGINE: MFR: FORD, MODEL LSG-875I-6005A, S/N 04781 A-05-RA, 132 BHP, FUEL: PROPANE, DRIVING A 76 KW GENERATOR. (971067-CCN-4/98)_x000D_ BLDG 1133 | K22: =IFERROR(IF(SEARCH(K$1,$J22)>0,1),0) -> 0 | L22: =IFERROR(IF(SEARCH(L$1,$J22)>0,1),0) -> 0 | M22: =IFERROR(IF(SEARCH(M$1,$J22)>0,1),0) -> 0 | N22: =IFERROR(IF(SEARCH(N$1,$J22)>0,1),0) -> 1 | O22: =SUM(K22:N22) -> 1 | P22: Propane | Q22: 76 | R22: 132 | S22: =IFERROR(IF(Q22<>"",Q22,R22*0.7457),"Unknown") -> 76 | Y22: =X22*S22 -> 0 | Z22: =IFERROR(INDEX(EFs!B:B,MATCH(P22,EFs!A:A,0))*Dataset!Y22/1000,0) -> 0 | AA22: 33.387723 | AB22: -117.44476 | AC22: 0.5 | AD22: place | AI22: Camp Pendleton | AJ22: CA | AK22: San Diego County | AL22: 92055 | AM22: US | AN22: TIGER/LineÂ® dataset from the US Census Bureau
A23: APCD2003-PTO-973507 | B23: Active | C23: 40025 | D23: [34W] Registered Engine (Rule 12) | E23: SD City Of Metro Wastewater Dept | F23: Civil Engineer | G23: 1795 Harbor Dr E San Diego, CA | H23: 92113 | I23: P | J23: CUMMINS NATURAL GAS ENGINE, MODEL G855, 220 HP, S/N 25208445. 973507AFS14JUN1999 071602AFS (CORRECT EQUIPMENT DESCRIPTION) | K23: =IFERROR(IF(SEARCH(K$1,$J23)>0,1),0) -> 0 | L23: =IFERROR(IF(SEARCH(L$1,$J23)>0,1),0) -> 0 | M23: =IFERROR(IF(SEARCH(M$1,$J23)>0,1),0) -> 1 | N23: =IFERROR(IF(SEARCH(N$1,$J23)>0,1),0) -> 0 | O23: =SUM(K23:N23) -> 1 | P23: Natural Gas | R23: 220 | S23: =IFERROR(IF(Q23<>"",Q23,R23*0.7457),"Unknown") -> 164.054 | T23: 44412 | U23: 232.50 | V23: 44412 | W23: 237.00 | X23: 4.5 | Y23: =X23*S23 -> 738.243 | Z23: =IFERROR(INDEX(EFs!B:B,MATCH(P23,EFs!A:A,0))*Dataset!Y23/1000,0) -> 0.5361532 | AA23: 32.699468 | AB23: -117.14955 | AC23: 1 | AD23: rooftop | AE23: 1795 | AF23: Harbor Dr | AI23: San Diego | AJ23: CA | AK23: San Diego County | AL23: 92113 | AM23: US | AN23: San Diego Geographic Information Source - JPA
A24: APCD2003-PTO-974008 | B24: Active | C24: 40025 | D24: [34W] Registered Engine (Rule 12) | E24: DEL CERRO CITY DEPT OF HIGHLANDS PUMP PLANT | G24: 6555 CRYSTALAIRE DR SAN DIEGO, CA | H24: 92120 | I24: J | J24: EMERGENCY GENERATOR: 240 BHP CUMMINS ENGINE, NATURAL GAS FIRED, MODEL GTA8.3 G5/GC2, S/N 45870458, WITH TURBOCHARGING AND AFTERCOOLING, DRIVING A150 KW GENERATOR. EAD 974008 2/9/00 | K24: =IFERROR(IF(SEARCH(K$1,$J24)>0,1),0) -> 0 | L24: =IFERROR(IF(SEARCH(L$1,$J24)>0,1),0) -> 0 | M24: =IFERROR(IF(SEARCH(M$1,$J24)>0,1),0) -> 1 | N24: =IFERROR(IF(SEARCH(N$1,$J24)>0,1),0) -> 0 | O24: =SUM(K24:N24) -> 1 | P24: Natural Gas | Q24: 150 | R24: 240 | S24: =IFERROR(IF(Q24<>"",Q24,R24*0.7457),"Unknown") -> 150 | T24: 44562 | U24: 691.70 | V24: 44562 | W24: 694.90 | X24: 3.2 | Y24: =X24*S24 -> 480 | Z24: =IFERROR(INDEX(EFs!B:B,MATCH(P24,EFs!A:A,0))*Dataset!Y24/1000,0) -> 0.34860275 | AA24: 32.788933 | AB24: -117.05578 | AC24: 1 | AD24: range_interpolation | AE24: 6555 | AF24: Crystalaire Dr | AI24: San Diego | AJ24: CA | AK24: San Diego County | AL24: 92120 | AM24: US | AN24: TIGER/LineÂ® dataset from the US Census Bureau
A25: APCD2003-PTO-974511 | B25: Active | C25: 40025 | D25: [34W] Registered Engine (Rule 12) | E25: USMC Base Public Utilities U29 | F25: Air Quality Section | G25: Building 610547 CAMP PENDLETON, CA | H25: 92055 | I25: A | J25: FORD PROPANE FIRED MODEL LSG875, GENERATOR S/N E6791J-001, 60 KW, 127.8 BHP. 145 PETERSON ST, SAN MATEO HOUSING 974511 AFS 27JAN2000 (BLDG 610547) | K25: =IFERROR(IF(SEARCH(K$1,$J25)>0,1),0) -> 0 | L25: =IFERROR(IF(SEARCH(L$1,$J25)>0,1),0) -> 0 | M25: =IFERROR(IF(SEARCH(M$1,$J25)>0,1),0) -> 0 | N25: =IFERROR(IF(SEARCH(N$1,$J25)>0,1),0) -> 1 | O25: =SUM(K25:N25) -> 1 | P25: Propane | Q25: 60 | R25: 127.8 | S25: =IFERROR(IF(Q25<>"",Q25,R25*0.7457),"Unknown") -> 60 | Y25: =X25*S25 -> 0 | Z25: =IFERROR(INDEX(EFs!B:B,MATCH(P25,EFs!A:A,0))*Dataset!Y25/1000,0) -> 0 | AA25: 33.387723 | AB25: -117.44476 | AC25: 0.5 | AD25: place | AI25: Camp Pendleton | AJ25: CA | AK25: San Diego County | AL25: 92055 | AM25: US | AN25: TIGER/LineÂ® dataset from the US Census Bureau
A26: APCD2003-PTO-974876 | B26: Active | C26: 40025 | D26: [34W] Registered Engine (Rule 12) | E26: USMC Base Marine Group Ops | F26: Air Quality Section | G26: Camp Pendleton Camp Pendleton, CA | H26: 92055 | I26: A | J26: EMERGENCY ENGINE GENERATOR, FUEL: NATURAL GAS, 495 HP, CUMMINS ENGINE, MODEL GTA19, S/N SN25247550. (BLDG. 210721) APPL# 974876 EFH 04/00 | K26: =IFERROR(IF(SEARCH(K$1,$J26)>0,1),0) -> 0 | L26: =IFERROR(IF(SEARCH(L$1,$J26)>0,1),0) -> 0 | M26: =IFERROR(IF(SEARCH(M$1,$J26)>0,1),0) -> 1 | N26: =IFERROR(IF(SEARCH(N$1,$J26)>0,1),0) -> 0 | O26: =SUM(K26:N26) -> 1 | P26: Natural Gas | R26: 495 | S26: =IFERROR(IF(Q26<>"",Q26,R26*0.7457),"Unknown") -> 369.1215 | Y26: =X26*S26 -> 0 | Z26: =IFERROR(INDEX(EFs!B:B,MATCH(P26,EFs!A:A,0))*Dataset!Y26/1000,0) -> 0 | AA26: 33.387723 | AB26: -117.44476 | AC26: 1 | AD26: place | AI26: Camp Pendleton | AJ26: CA | AK26: San Diego County | AL26: 92055 | AM26: US | AN26: TIGER/LineÂ® dataset from the US Census Bureau
A27: APCD2003-PTO-974877 | B27: Active | C27: 40025 | D27: [34H] California Certified Emergency Standby Engine | E27: USMC Base Marine Group Ops | F27: Air Quality Section | G27: Building 217201 Camp Pendleton, CA | H27: 92055 | I27: A | J27: Emergency Engine: Power Solutions ? Generac, Model: SG500, 777 BHP, NG fired, Engine Family No. LGNXB25.82C1, S/N 3005494043; certified with a 3-way catalyst and air-fuel ratio controller; driving a 500-kW electrical generator. | K27: =IFERROR(IF(SEARCH(K$1,$J27)>0,1),0) -> 0 | L27: =IFERROR(IF(SEARCH(L$1,$J27)>0,1),0) -> 0 | M27: =IFERROR(IF(SEARCH(M$1,$J27)>0,1),0) -> 0 | N27: =IFERROR(IF(SEARCH(N$1,$J27)>0,1),0) -> 0 | O27: =SUM(K27:N27) -> 0 | P27: Natural Gas | Q27: 500 | R27: 777 | S27: =IFERROR(IF(Q27<>"",Q27,R27*0.7457),"Unknown") -> 500 | Y27: =X27*S27 -> 0 | Z27: =IFERROR(INDEX(EFs!B:B,MATCH(P27,EFs!A:A,0))*Dataset!Y27/1000,0) -> 0 | AA27: 33.387723 | AB27: -117.44476 | AC27: 0.5 | AD27: place | AI27: Camp Pendleton | AJ27: CA | AK27: San Diego County | AL27: 92055 | AM27: US | AN27: TIGER/LineÂ® dataset from the US Census Bureau
A28: APCD2003-PTO-976368 | B28: Active | C28: 40025 | D28: [34W] Registered Engine (Rule 12) | E28: SD City Of Metro Wastewater Dept | G28: 2802 Bayside Walk San Diego, CA | H28: 92109 | I28: I | J28: EMERGENCY STANDBY ENGINE: FORD NATURAL GAS ENGINE, MODEL LSG-8751-6005-A, 165 BHP, DRIVING A GENERATOR. (976368-CCN-11/01) | K28: =IFERROR(IF(SEARCH(K$1,$J28)>0,1),0) -> 0 | L28: =IFERROR(IF(SEARCH(L$1,$J28)>0,1),0) -> 0 | M28: =IFERROR(IF(SEARCH(M$1,$J28)>0,1),0) -> 1 | N28: =IFERROR(IF(SEARCH(N$1,$J28)>0,1),0) -> 0 | O28: =SUM(K28:N28) -> 1 | P28: Natural Gas | R28: 165 | S28: =IFERROR(IF(Q28<>"",Q28,R28*0.7457),"Unknown") -> 123.0405 | Y28: =X28*S28 -> 0 | Z28: =IFERROR(INDEX(EFs!B:B,MATCH(P28,EFs!A:A,0))*Dataset!Y28/1000,0) -> 0 | AA28: 32.763541 | AB28: -117.25006 | AC28: 1 | AD28: range_interpolation | AE28: 2802 | AF28: Bayside Walk | AI28: San Diego | AJ28: CA | AK28: San Diego County | AL28: 92109 | AM28: US | AN28: TIGER/LineÂ® dataset from the US Census Bureau
A29: APCD2003-PTO-976369 | B29: Active | C29: 40025 | D29: [34W] Registered Engine (Rule 12) | E29: SD City Of Metro Wastewater Dept | G29: 102 Fern Glen La Jolla, CA | H29: 92037 | I29: I | J29: EMERGENCY STANDBY ENGINE: GENERAC NATURAL GAS ENGINE, MODEL 7.4L, S/N A4350, 165 BHP, DRIVING A GENERATOR. (976369-CCN-11/01) | K29: =IFERROR(IF(SEARCH(K$1,$J29)>0,1),0) -> 0 | L29: =IFERROR(IF(SEARCH(L$1,$J29)>0,1),0) -> 0 | M29: =IFERROR(IF(SEARCH(M$1,$J29)>0,1),0) -> 1 | N29: =IFERROR(IF(SEARCH(N$1,$J29)>0,1),0) -> 0 | O29: =SUM(K29:N29) -> 1 | P29: Natural Gas | R29: 165 | S29: =IFERROR(IF(Q29<>"",Q29,R29*0.7457),"Unknown") -> 123.0405 | T29: 44350 | U29: 34.60 | V29: 44350 | W29: 44.00 | X29: 9.4 | Y29: =X29*S29 -> 1156.5807 | Z29: =IFERROR(INDEX(EFs!B:B,MATCH(P29,EFs!A:A,0))*Dataset!Y29/1000,0) -> 0.83997335 | AA29: 32.834131 | AB29: -117.28134 | AC29: 1 | AD29: range_interpolation | AE29: 102 | AF29: Fern Gln | AI29: LA Jolla | AJ29: CA | AK29: San Diego County | AL29: 92037 | AM29: US | AN29: TIGER/LineÂ® dataset from the US Census Bureau
A30: APCD2003-PTO-976371 | B30: Active | C30: 40025 | D30: [34W] Registered Engine (Rule 12) | E30: SD City Of Metro Wastewater Dept | G30: 5995 Camino De La Costa La Jolla, CA | H30: 92037 | I30: I | J30: EMERGENCY STANDBY ENGINE: FORD NATURAL GAS ENGINE, MODEL LSG-8751-6005-A, S/N 07413, 90 BHP, DRIVING A GENERATOR. (976371-CCN-11/01) | K30: =IFERROR(IF(SEARCH(K$1,$J30)>0,1),0) -> 0 | L30: =IFERROR(IF(SEARCH(L$1,$J30)>0,1),0) -> 0 | M30: =IFERROR(IF(SEARCH(M$1,$J30)>0,1),0) -> 1 | N30: =IFERROR(IF(SEARCH(N$1,$J30)>0,1),0) -> 0 | O30: =SUM(K30:N30) -> 1 | P30: Natural Gas | R30: 90 | S30: =IFERROR(IF(Q30<>"",Q30,R30*0.7457),"Unknown") -> 67.113 | T30: 44350 | U30: 256.20 | V30: 44350 | W30: 263.20 | X30: 7 | Y30: =X30*S30 -> 469.791 | Z30: =IFERROR(INDEX(EFs!B:B,MATCH(P30,EFs!A:A,0))*Dataset!Y30/1000,0) -> 0.3411884 | AA30: 32.81874 | AB30: -117.27591 | AC30: 0.9 | AD30: nearest_rooftop_match | AE30: 5998 | AF30: Camino De La Costa | AI30: LA Jolla | AJ30: CA | AK30: San Diego County | AL30: 92037 | AM30: US | AN30: San Diego Geographic Information Source - JPA
A31: APCD2003-PTO-976375 | B31: Active | C31: 40025 | D31: [34W] Registered Engine (Rule 12) | E31: SD City Of Metro Wastewater Dept | G31: 1840 Mission Bay Dr W San Diego, CA | H31: 92109 | I31: I | J31: EMERGENCY STANDBY ENGINE: FORD NATURAL GAS ENGINE, MODEL LSG-8751-6005-A, 135 BHP, DRIVING A GENERATOR, (976375-CCN-11/01). Serial number: 00937 G-12-RL | K31: =IFERROR(IF(SEARCH(K$1,$J31)>0,1),0) -> 0 | L31: =IFERROR(IF(SEARCH(L$1,$J31)>0,1),0) -> 0 | M31: =IFERROR(IF(SEARCH(M$1,$J31)>0,1),0) -> 1 | N31: =IFERROR(IF(SEARCH(N$1,$J31)>0,1),0) -> 0 | O31: =SUM(K31:N31) -> 1 | P31: Natural Gas | R31: 135 | S31: =IFERROR(IF(Q31<>"",Q31,R31*0.7457),"Unknown") -> 100.6695 | Y31: =X31*S31 -> 0 | Z31: =IFERROR(INDEX(EFs!B:B,MATCH(P31,EFs!A:A,0))*Dataset!Y31/1000,0) -> 0 | AA31: 32.764046 | AB31: -117.23305 | AC31: 0.9 | AD31: range_interpolation | AE31: 1840 | AF31: W Mission Bay Dr | AI31: San Diego | AJ31: CA | AK31: San Diego County | AL31: 92109 | AM31: US | AN31: TIGER/LineÂ® dataset from the US Census Bureau
A32: APCD2003-PTO-976376 | B32: Active | C32: 40025 | D32: [34H] California Certified Emergency Standby Engine | E32: City of SD, Public Utilities Department | F32: Facility Manager SPS 31 | G32: 6652 CALLE DE LINEA SAN DIEGO, CA | H32: 92154 | I32: S | J32: Emergency Engine: Kohler, Model: KG6208TAHD 6.2L, 202 BHP, Natural Gas fired, Engine Family No. LKHXB06.2HNG, S/N OE20201586; certified with an electronic air to fuel controller and TWC driving a 100-kW generator. | K32: =IFERROR(IF(SEARCH(K$1,$J32)>0,1),0) -> 0 | L32: =IFERROR(IF(SEARCH(L$1,$J32)>0,1),0) -> 0 | M32: =IFERROR(IF(SEARCH(M$1,$J32)>0,1),0) -> 1 | N32: =IFERROR(IF(SEARCH(N$1,$J32)>0,1),0) -> 0 | O32: =SUM(K32:N32) -> 1 | P32: Natural Gas | Q32: 100 | R32: 202 | S32: =IFERROR(IF(Q32<>"",Q32,R32*0.7457),"Unknown") -> 100 | T32: 44406 | U32: 0.80 | V32: 44776 | W32: 19.20 | X32: 18.4 | Y32: =X32*S32 -> 1840 | Z32: =IFERROR(INDEX(EFs!B:B,MATCH(P32,EFs!A:A,0))*Dataset!Y32/1000,0) -> 1.3363105 | AA32: 32.548779 | AB32: -116.99539 | AC32: 0.7 | AD32: nearest_rooftop_match | AE32: 6754 | AF32: Calle De Linea | AI32: San Diego | AJ32: CA | AK32: San Diego County | AL32: 92154 | AM32: US | AN32: San Diego Geographic Information Source - JPA
A33: APCD2003-PTO-976377 | B33: Active | C33: 40025 | D33: [34W] Registered Engine (Rule 12) | E33: SD City Of Metro Wastewater Dept | G33: 3214 Bayside Walk San Diego, CA | H33: 92109 | I33: I | J33: EMERGENCY STANDBY ENGINE: FORD NATURAL GAS ENGINE, MODEL LSG-8751-6005-A, S/N 17448, 135 BHP, DRIVING A GENERATOR. (976377-CCN-11/01) | K33: =IFERROR(IF(SEARCH(K$1,$J33)>0,1),0) -> 0 | L33: =IFERROR(IF(SEARCH(L$1,$J33)>0,1),0) -> 0 | M33: =IFERROR(IF(SEARCH(M$1,$J33)>0,1),0) -> 1 | N33: =IFERROR(IF(SEARCH(N$1,$J33)>0,1),0) -> 0 | O33: =SUM(K33:N33) -> 1 | P33: Natural Gas | R33: 135 | S33: =IFERROR(IF(Q33<>"",Q33,R33*0.7457),"Unknown") -> 100.6695 | Y33: =X33*S33 -> 0 | Z33: =IFERROR(INDEX(EFs!B:B,MATCH(P33,EFs!A:A,0))*Dataset!Y33/1000,0) -> 0 | AA33: 32.772405 | AB33: -117.2498 | AC33: 1 | AD33: range_interpolation | AE33: 3214 | AF33: Bayside Walk | AI33: San Diego | AJ33: CA | AK33: San Diego County | AL33: 92109 | AM33: US | AN33: TIGER/LineÂ® dataset from the US Census Bureau
A34: APCD2003-PTO-976378 | B34: Active | C34: 40025 | D34: [34W] Registered Engine (Rule 12) | E34: SD City Of Metro Wastewater Dept | G34: 5060 Pt Loma Blvd W San Diego, CA | H34: 92107 | I34: I | J34: EMERGENCY STANDBY ENGINE: FORD NATURAL GAS ENGINE, MODEL LSG-8751-6005-A, S/N 15291, 135 BHP, DRIVING A GENERATOR. (976378-CCN-11/01) | K34: =IFERROR(IF(SEARCH(K$1,$J34)>0,1),0) -> 0 | L34: =IFERROR(IF(SEARCH(L$1,$J34)>0,1),0) -> 0 | M34: =IFERROR(IF(SEARCH(M$1,$J34)>0,1),0) -> 1 | N34: =IFERROR(IF(SEARCH(N$1,$J34)>0,1),0) -> 0 | O34: =SUM(K34:N34) -> 1 | P34: Natural Gas | R34: 135 | S34: =IFERROR(IF(Q34<>"",Q34,R34*0.7457),"Unknown") -> 100.6695 | T34: 44350 | U34: 278.60 | V34: 44350 | W34: 282.70 | X34: 4.1 | Y34: =X34*S34 -> 412.74495 | Z34: =IFERROR(INDEX(EFs!B:B,MATCH(P34,EFs!A:A,0))*Dataset!Y34/1000,0) -> 0.29975838 | AA34: 32.724103 | AB34: -117.17091 | AC34: 0.5 | AD34: place | AI34: San Diego | AJ34: CA | AK34: San Diego County | AL34: 92101 | AM34: US | AN34: TIGER/LineÂ® dataset from the US Census Bureau
A35: APCD2003-PTO-976531 | B35: Active | C35: 40025 | D35: [34H] California Certified Emergency Standby Engine | E35: Union Bank Of California | F35: Property Manager | G35: 8954 Rio San Diego San Diego, CA | H35: 92108 | I35: M | J35: EMERGENCY STANDBY ENGINE: CATERPILLAR DIESEL ENGINE, MODEL 3406, S/N 1LSO1576, RATED AT 519 BHP, EPA TIER 1 CERTIFIED OF ENGINE FAMILY NUMBER 1CPXL14.6ESK, EQUIPPED WITH TURBOCHARGER, DRIVING A 350 KW GENERATOR (976531-CCN-10/02) 17CCR93115SJE8/06 | K35: =IFERROR(IF(SEARCH(K$1,$J35)>0,1),0) -> 1 | L35: =IFERROR(IF(SEARCH(L$1,$J35)>0,1),0) -> 0 | M35: =IFERROR(IF(SEARCH(M$1,$J35)>0,1),0) -> 0 | N35: =IFERROR(IF(SEARCH(N$1,$J35)>0,1),0) -> 0 | O35: =SUM(K35:N35) -> 1 | P35: Diesel | Q35: 350 | R35: 519 | S35: =IFERROR(IF(Q35<>"",Q35,R35*0.7457),"Unknown") -> 350 | Y35: =X35*S35 -> 0 | Z35: =IFERROR(INDEX(EFs!B:B,MATCH(P35,EFs!A:A,0))*Dataset!Y35/1000,0) -> 0 | AA35: 32.776536 | AB35: -117.13599 | AC35: 1 | AD35: rooftop | AE35: 8954 | AF35: Rio San Diego Dr | AI35: San Diego | AJ35: CA | AK35: San Diego County | AL35: 92108 | AM35: US | AN35: San Diego Geographic Information Source - JPA
A36: APCD2003-PTO-976877 | B36: Active | C36: 40025 | D36: [34H] California Certified Emergency Standby Engine | E36: Fallbrook PUD - Shady Lane Lift Station | F36: Soleil Develle | G36: 739 Shady Lane Fallbrook, CA | H36: 92028 | I36: A | J36: Emergency Diesel Engine Generator: Kohler, Model KDI3404TCR rated at 94 bhp, S/N 4819702450 , Engine Family: JKHXL3.36TCR, EPA Tier 3 certified engine; driving an 60-kW emergency electrical generator. | K36: =IFERROR(IF(SEARCH(K$1,$J36)>0,1),0) -> 1 | L36: =IFERROR(IF(SEARCH(L$1,$J36)>0,1),0) -> 0 | M36: =IFERROR(IF(SEARCH(M$1,$J36)>0,1),0) -> 0 | N36: =IFERROR(IF(SEARCH(N$1,$J36)>0,1),0) -> 0 | O36: =SUM(K36:N36) -> 1 | P36: Diesel | Q36: 60 | R36: 94 | S36: =IFERROR(IF(Q36<>"",Q36,R36*0.7457),"Unknown") -> 60 | T36: 44406 | U36: 50.10 | V36: 44406 | W36: 62.80 | X36: 12.7 | Y36: =X36*S36 -> 762 | Z36: =IFERROR(INDEX(EFs!B:B,MATCH(P36,EFs!A:A,0))*Dataset!Y36/1000,0) -> 0.69219541 | AA36: 33.389361 | AB36: -117.25547 | AC36: 1 | AD36: rooftop | AE36: 739 | AF36: Shady Ln | AI36: Fallbrook | AJ36: CA | AK36: San Diego County | AL36: 92028 | AM36: US | AN36: Sandoval
A37: APCD2003-PTO-977041 | B37: Active | C37: 40025 | D37: [34W] Registered Engine (Rule 12) | E37: Ramona Municipal Water District | F37: Tom McKernan | G37: 16424 Woodson DR N Ramona, CA | H37: 92065 | I37: F | J37: EMERGENCY GENERATOR FORD MODEL CSG-6491-6005-F S/N 01199-G-22-RB. HP RATING 95. PROPANE FUELED. | K37: =IFERROR(IF(SEARCH(K$1,$J37)>0,1),0) -> 0 | L37: =IFERROR(IF(SEARCH(L$1,$J37)>0,1),0) -> 0 | M37: =IFERROR(IF(SEARCH(M$1,$J37)>0,1),0) -> 0 | N37: =IFERROR(IF(SEARCH(N$1,$J37)>0,1),0) -> 1 | O37: =SUM(K37:N37) -> 1 | P37: Propane | R37: 95 | S37: =IFERROR(IF(Q37<>"",Q37,R37*0.7457),"Unknown") -> 70.8415 | T37: 44532 | U37: 632.70 | V37: 44532 | W37: 639.30 | X37: 6.6 | Y37: =X37*S37 -> 467.5539 | Z37: =IFERROR(INDEX(EFs!B:B,MATCH(P37,EFs!A:A,0))*Dataset!Y37/1000,0) -> 0.38521766 | AA37: 33.015616 | AB37: -116.95938 | AC37: 0.95 | AD37: rooftop | AE37: 16424 | AF37: N Woodson Dr | AI37: Ramona | AJ37: CA | AK37: San Diego County | AL37: 92065 | AM37: US | AN37: San Diego Geographic Information Source - JPA
A38: APCD2003-PTO-977043 | B38: Active | C38: 40025 | D38: [34W] Registered Engine (Rule 12) | E38: Ramona Municipal Water District | F38: Facility Manager | G38: 24462 San Vicente RD Ramona, CA | H38: 92065 | I38: F | J38: EMERGENCY GENERATOR GENERAC. MODEL : CA3797. S/N: 2039349. PROPANE FUELED._x000D_ENGINE MODEL NUMBER 4.3L, S/N A3797. | K38: =IFERROR(IF(SEARCH(K$1,$J38)>0,1),0) -> 0 | L38: =IFERROR(IF(SEARCH(L$1,$J38)>0,1),0) -> 0 | M38: =IFERROR(IF(SEARCH(M$1,$J38)>0,1),0) -> 0 | N38: =IFERROR(IF(SEARCH(N$1,$J38)>0,1),0) -> 1 | O38: =SUM(K38:N38) -> 1 | P38: Propane | R38: Unknown | S38: =IFERROR(IF(Q38<>"",Q38,R38*0.7457),"Unknown") -> Unknown | T38: 44532 | U38: 443.40 | V38: 44532 | W38: 449.00 | X38: 5.6 | Y38: =X38*S38 -> #VALUE! | Z38: =IFERROR(INDEX(EFs!B:B,MATCH(P38,EFs!A:A,0))*Dataset!Y38/1000,0) -> 0 | AA38: 33.000872 | AB38: -116.80008 | AC38: 1 | AD38: rooftop | AE38: 24462 | AF38: San Vicente Rd | AI38: Ramona | AJ38: CA | AK38: San Diego County | AL38: 92065 | AM38: US | AN38: San Diego Geographic Information Source - JPA
A39: APCD2003-PTO-977127 | B39: Active | C39: 40025 | D39: [34C] Emergency Standby Engine | E39: SD City Of | F39: Facility Manager | G39: 6689 Neptune Place San Diego, CA | H39: 92037 | I39: I | J39: EMERGENCY STANDBY ENGINE: GENERAL MOTORS ENGINE, NATURAL GAS FUELED, MODEL VORTEC 8.1 LITER, S/N 8.1L-05331, RATED AT 136 BHP, EQUIPPED WITH THREE-WAY CATALYTIC CONVERTER, DRIVING AN 80 KW GENERATOR. (977127-CCN-9/03) | K39: =IFERROR(IF(SEARCH(K$1,$J39)>0,1),0) -> 0 | L39: =IFERROR(IF(SEARCH(L$1,$J39)>0,1),0) -> 0 | M39: =IFERROR(IF(SEARCH(M$1,$J39)>0,1),0) -> 1 | N39: =IFERROR(IF(SEARCH(N$1,$J39)>0,1),0) -> 0 | O39: =SUM(K39:N39) -> 1 | P39: Natural Gas | Q39: 80 | R39: 136 | S39: =IFERROR(IF(Q39<>"",Q39,R39*0.7457),"Unknown") -> 80 | T39: 44350 | U39: 260.40 | V39: 44350 | W39: 264.10 | X39: 3.7 | Y39: =X39*S39 -> 296 | Z39: =IFERROR(INDEX(EFs!B:B,MATCH(P39,EFs!A:A,0))*Dataset!Y39/1000,0) -> 0.21497169 | AA39: 32.828222 | AB39: -117.2801 | AC39: 0.9 | AD39: range_interpolation | AE39: 6689 | AF39: Neptune Pl | AI39: LA Jolla | AJ39: CA | AK39: San Diego County | AL39: 92037 | AM39: US | AN39: TIGER/LineÂ® dataset from the US Census Bureau
A40: APCD2003-PTO-977370 | B40: Active | C40: 40025 | D40: [34W] Registered Engine (Rule 12) | E40: Rainbow Municipal Water District | F40: Jeff Stacy | G40: 4198 Lake Circle Dr Fallbrook, CA | H40: 92028 | I40: A | J40: EMERGENCY ENGINE: MFR: HINO, MODEL: EK130, SERIAL: A10615, Generac serial number 76815, FUEL: PROPANE, _x000D_DISPLACEMENT: 13.3 LITERS, CONFIGURATION: INLINE 6 CYLINDER, HP RATING= 177.5, _x000D_FOR A 125 KW GENERATOR (MFR: GENERAC; MODEL: 3285B1263B, S/N: AD205193SPK) SEWER LIFT STATION #5. | K40: =IFERROR(IF(SEARCH(K$1,$J40)>0,1),0) -> 0 | L40: =IFERROR(IF(SEARCH(L$1,$J40)>0,1),0) -> 0 | M40: =IFERROR(IF(SEARCH(M$1,$J40)>0,1),0) -> 0 | N40: =IFERROR(IF(SEARCH(N$1,$J40)>0,1),0) -> 1 | O40: =SUM(K40:N40) -> 1 | P40: Propane | Q40: 125 | R40: 177.5 | S40: =IFERROR(IF(Q40<>"",Q40,R40*0.7457),"Unknown") -> 125 | Y40: =X40*S40 -> 0 | Z40: =IFERROR(INDEX(EFs!B:B,MATCH(P40,EFs!A:A,0))*Dataset!Y40/1000,0) -> 0 | AA40: 33.324158 | AB40: -117.15668 | AC40: 1 | AD40: range_interpolation | AE40: 4198 | AF40: Lake Circle Dr | AI40: Fallbrook | AJ40: CA | AK40: San Diego County | AL40: 92028 | AM40: US | AN40: TIGER/LineÂ® dataset from the US Census Bureau
A41: APCD2003-PTO-977371 | B41: Active | C41: 40025 | D41: [34W] Registered Engine (Rule 12) | E41: Rainbow Municipal Water District | F41: Jeff Stacy | G41: 211 1/2 Manzano St Fallbrook, CA | H41: 92028 | I41: A | J41: EMERGENCY ENGINE: MFR: GENERAL MOTORS/GENERAC, Part No. 76785, DISPLACEMENT: 5.0 LITERS, CONFIGURATION: V-8, FUEL: NATURAL GAS, HP RATING= 112 FOR A GENERATOR (MFR: GENERAC, MODEL: 92022075, SERIAL: 2003349) SEWER LIFT STATION #4 | K41: =IFERROR(IF(SEARCH(K$1,$J41)>0,1),0) -> 0 | L41: =IFERROR(IF(SEARCH(L$1,$J41)>0,1),0) -> 0 | M41: =IFERROR(IF(SEARCH(M$1,$J41)>0,1),0) -> 1 | N41: =IFERROR(IF(SEARCH(N$1,$J41)>0,1),0) -> 0 | O41: =SUM(K41:N41) -> 1 | P41: Natural Gas | R41: 112 | S41: =IFERROR(IF(Q41<>"",Q41,R41*0.7457),"Unknown") -> 83.5184 | Y41: =X41*S41 -> 0 | Z41: =IFERROR(INDEX(EFs!B:B,MATCH(P41,EFs!A:A,0))*Dataset!Y41/1000,0) -> 0 | AA41: 33.246382 | AB41: -117.29723 | AC41: 0.8 | AD41: nearest_rooftop_match | AE41: 210 | AF41: Manzanita Dr | AI41: Oceanside | AJ41: CA | AK41: San Diego County | AL41: 92057 | AM41: US | AN41: San Diego Geographic Information Source - JPA
A42: APCD2003-PTO-977686 | B42: Active | C42: 40025 | D42: [34C] Emergency Standby Engine | E42: Target Store T1485 | F42: Store Manager | G42: 9846 Mission Gorge Road Santee, CA | H42: 92071 | I42: H | J42: INTERNAL COMBUSTION ENGINE. MAKE: FORD. MODEL: ESG-6421-6005-A,, SERIAL NO: 01-12-038486, 97 BHP. NATURAL GAS FUELED. NATURALLY ASPIRATED. MANUFACTURE YEAR: DECEMBER 2001. EQUIPPED WITH AN AIR TO FUEL RATIO CONTROLLER AND A 3 WAY CATALYTIC CONVERTER. DRIVES AN ELECTRICAL EMERGENCY 35KW GENERATOR RATED AT 35 KW. | K42: =IFERROR(IF(SEARCH(K$1,$J42)>0,1),0) -> 0 | L42: =IFERROR(IF(SEARCH(L$1,$J42)>0,1),0) -> 0 | M42: =IFERROR(IF(SEARCH(M$1,$J42)>0,1),0) -> 1 | N42: =IFERROR(IF(SEARCH(N$1,$J42)>0,1),0) -> 0 | O42: =SUM(K42:N42) -> 1 | P42: Natural Gas | Q42: 35 | R42: 97 | S42: =IFERROR(IF(Q42<>"",Q42,R42*0.7457),"Unknown") -> 35 | T42: 44562 | U42: 239.80 | V42: 44562 | W42: 241.40 | X42: 1.6 | Y42: =X42*S42 -> 56 | Z42: =IFERROR(INDEX(EFs!B:B,MATCH(P42,EFs!A:A,0))*Dataset!Y42/1000,0) -> 0.04067032 | AA42: 32.842136 | AB42: -116.98257 | AC42: 1 | AD42: rooftop | AE42: 9846 | AF42: Mission Gorge Rd | AI42: Santee | AJ42: CA | AK42: San Diego County | AL42: 92071 | AM42: US | AN42: San Diego Geographic Information Source - JPA
A43: APCD2003-PTO-977867 | B43: Active | C43: 40025 | D43: [34C] Emergency Standby Engine | E43: SD City of Metro Wastewater Dept | F43: Rupic Branko | G43: 2799 Carleton St San Diego, CA | H43: 92106 | I43: I | J43: EMERGENCY ENGINE: GENERAL MOTORS, MODEL VORTEC 5.7L, 105 BHP, NATURAL GAS FIRED, S/N 5.71-06044, DRIVING A 60-KW ELECTRIC GENERATOR. (977867 ALC 06/02) | K43: =IFERROR(IF(SEARCH(K$1,$J43)>0,1),0) -> 0 | L43: =IFERROR(IF(SEARCH(L$1,$J43)>0,1),0) -> 0 | M43: =IFERROR(IF(SEARCH(M$1,$J43)>0,1),0) -> 1 | N43: =IFERROR(IF(SEARCH(N$1,$J43)>0,1),0) -> 0 | O43: =SUM(K43:N43) -> 1 | P43: Natural Gas | Q43: 60 | R43: 105 | S43: =IFERROR(IF(Q43<>"",Q43,R43*0.7457),"Unknown") -> 60 | T43: 44350 | U43: 261.00 | V43: 44350 | W43: 274.50 | X43: 13.5 | Y43: =X43*S43 -> 810 | Z43: =IFERROR(INDEX(EFs!B:B,MATCH(P43,EFs!A:A,0))*Dataset!Y43/1000,0) -> 0.58826713 | AA43: 32.721819 | AB43: -117.22854 | AC43: 1 | AD43: range_interpolation | AE43: 2799 | AF43: Carleton St | AI43: San Diego | AJ43: CA | AK43: San Diego County | AL43: 92106 | AM43: US | AN43: TIGER/LineÂ® dataset from the US Census Bureau
A44: APCD2003-PTO-977978 | B44: Active | C44: 40025 | D44: [34C] Emergency Standby Engine | E44: City of Escondido - East Grove PS | F44: Reed Harlan | G44: 552 S Hidden Trail Rd Escondido, CA | H44: 92027 | I44: D | J44: EMERGENCY STANDY ENGINE: _x000D_Mfr: Cummins, _x000D_Model: GTA-8.3-LC-G1 _x000D_S/N 46134017, _x000D_Fuel: Propane, _x000D_Output: 202 BHP, _x000D_ with turbocharging, air-to-fuel ratio controller and MINE X BYDCL Industries NSCR 3-Way Catalyst, Catalytic Converter for CO, HC, and NOx Control, driving a 125kW generator. _x000D__x000D_977978 EAD 062603 | K44: =IFERROR(IF(SEARCH(K$1,$J44)>0,1),0) -> 0 | L44: =IFERROR(IF(SEARCH(L$1,$J44)>0,1),0) -> 0 | M44: =IFERROR(IF(SEARCH(M$1,$J44)>0,1),0) -> 0 | N44: =IFERROR(IF(SEARCH(N$1,$J44)>0,1),0) -> 1 | O44: =SUM(K44:N44) -> 1 | P44: Propane | Q44: 125 | R44: 202 | S44: =IFERROR(IF(Q44<>"",Q44,R44*0.7457),"Unknown") -> 125 | T44: 44448 | U44: 274.20 | V44: 44448 | W44: 279.80 | X44: 5.6 | Y44: =X44*S44 -> 700 | Z44: =IFERROR(INDEX(EFs!B:B,MATCH(P44,EFs!A:A,0))*Dataset!Y44/1000,0) -> 0.57673 | AA44: 33.140345 | AB44: -117.02192 | AC44: 1 | AD44: rooftop | AE44: 552 | AF44: S Hidden Trails Rd S | AI44: Escondido | AJ44: CA | AK44: San Diego County | AL44: 92027 | AM44: US | AN44: San Diego Geographic Information Source - JPA
A45: APCD2003-PTO-978142 | B45: Active | C45: 40025 | D45: [34W] Registered Engine (Rule 12) | E45: SD CO OF DPW WASTEWATER MGMT | F45: Facility Manager | G45: 411 RAMONA AV SPRING VALLEY, CA | H45: 91978 | I45: Q | J45: INTERNAL COMBUSTION ENGINE. MAKE: FORD. MODEL: LSG-8751-6005-A. SERIAL NO. 09241-A-29-TR. HP RATING: 161 HP. LIQUIFIED PETROLEUM GAS FUELED ENGINE. ENGINE POWERS A GENERATOR AT WASTEWATER PUMP STATION. | K45: =IFERROR(IF(SEARCH(K$1,$J45)>0,1),0) -> 0 | L45: =IFERROR(IF(SEARCH(L$1,$J45)>0,1),0) -> 1 | M45: =IFERROR(IF(SEARCH(M$1,$J45)>0,1),0) -> 0 | N45: =IFERROR(IF(SEARCH(N$1,$J45)>0,1),0) -> 0 | O45: =SUM(K45:N45) -> 1 | P45: LPG | R45: 161 | S45: =IFERROR(IF(Q45<>"",Q45,R45*0.7457),"Unknown") -> 120.0577 | T45: 44550 | U45: 323.00 | V45: 44550 | W45: 334.90 | X45: 11.9 | Y45: =X45*S45 -> 1428.6866 | Z45: =IFERROR(INDEX(EFs!B:B,MATCH(P45,EFs!A:A,0))*Dataset!Y45/1000,0) -> 1.4182796 | AA45: 32.704309 | AB45: -116.99494 | AC45: 1 | AD45: range_interpolation | AE45: 411 | AF45: Ramona Ave | AI45: Spring Valley | AJ45: CA | AK45: San Diego County | AL45: 91977 | AM45: US | AN45: TIGER/LineÂ® dataset from the US Census Bureau
A46: APCD2003-PTO-978146 | B46: Active | C46: 40025 | D46: [34W] Registered Engine (Rule 12) | E46: SD CO Of DPW Wastewater Mgmt | F46: General Manager | G46: 15935 Spring Oak Rd #L El Cajon, CA | H46: 92021 | I46: L | J46: INTERNAL COMBUSTION ENGINE. MAKE: FORD. MODEL: LSG-4231-6005-F. SERIAL NO 02315-G-25-TR. HP RATING: 82. NATURAL GAS FUELED. POWERS A GENERATOR LOCATED AT WASTEWATER PUMP STATION. | K46: =IFERROR(IF(SEARCH(K$1,$J46)>0,1),0) -> 0 | L46: =IFERROR(IF(SEARCH(L$1,$J46)>0,1),0) -> 0 | M46: =IFERROR(IF(SEARCH(M$1,$J46)>0,1),0) -> 1 | N46: =IFERROR(IF(SEARCH(N$1,$J46)>0,1),0) -> 0 | O46: =SUM(K46:N46) -> 1 | P46: Natural Gas | R46: 82 | S46: =IFERROR(IF(Q46<>"",Q46,R46*0.7457),"Unknown") -> 61.1474 | T46: 44783 | U46: 419.20 | V46: 44783 | W46: 420.90 | X46: 1.7 | Y46: =X46*S46 -> 103.95058 | Z46: =IFERROR(INDEX(EFs!B:B,MATCH(P46,EFs!A:A,0))*Dataset!Y46/1000,0) -> 0.075494703 | AA46: 32.861198 | AB46: -116.82487 | AC46: 1 | AD46: rooftop | AE46: 15935 | AF46: Spring Oaks Rd | AG46: # | AH46: L | AI46: El Cajon | AJ46: CA | AK46: San Diego County | AL46: 92021 | AM46: US | AN46: San Diego Geographic Information Source - JPA
A47: APCD2003-PTO-978231 | B47: Active | C47: 40025 | D47: [34W] Registered Engine (Rule 12) | E47: City of Escondido - LS#04 | F47: Facility Manager | G47: 1750 W. El Norte Pkwy Escondido, CA | H47: 92026 | I47: B | J47: EMERGENCY STANDBY ENGINE: GENERAL MOTORS MODEL 8.1 L, S/N 8.1 L-05200, 80 HP, PROPANE FIRED, EXISTING ENGINE SINCE AT LEAST 1994. 978231 AFS 09JUL2002 | K47: =IFERROR(IF(SEARCH(K$1,$J47)>0,1),0) -> 0 | L47: =IFERROR(IF(SEARCH(L$1,$J47)>0,1),0) -> 0 | M47: =IFERROR(IF(SEARCH(M$1,$J47)>0,1),0) -> 0 | N47: =IFERROR(IF(SEARCH(N$1,$J47)>0,1),0) -> 1 | O47: =SUM(K47:N47) -> 1 | P47: Propane | R47: 80 | S47: =IFERROR(IF(Q47<>"",Q47,R47*0.7457),"Unknown") -> 59.656 | T47: 44328 | U47: 374.90 | V47: 44679 | W47: 390.60 | X47: 15.7 | Y47: =X47*S47 -> 936.5992 | Z47: =IFERROR(INDEX(EFs!B:B,MATCH(P47,EFs!A:A,0))*Dataset!Y47/1000,0) -> 0.77166408 | AA47: 33.147317 | AB47: -117.10845 | AC47: 1 | AD47: range_interpolation | AE47: 1750 | AF47: W El Norte Pkwy | AI47: Escondido | AJ47: CA | AK47: San Diego County | AL47: 92026 | AM47: US | AN47: TIGER/LineÂ® dataset from the US Census Bureau
A48: APCD2003-PTO-978480 | B48: Active | C48: 40025 | D48: [34H] California Certified Emergency Standby Engine | E48: University of California San Diego | F48: Valerie Fanning | G48: 9500 Gilman Drive ECUP La Jolla, CA | H48: 92093 | I48: I | J48: Emergency standby engine: Caterpillar, model 3508B, S/N FZ01523, diesel fired, rated at 1480 bhp, EPA certified of family number 1CPXL34.5ERK, turbocharged, aftercooled, driving a 1000 kw generator. (978480-3/03)17ccr93115sje03/06 | K48: =IFERROR(IF(SEARCH(K$1,$J48)>0,1),0) -> 1 | L48: =IFERROR(IF(SEARCH(L$1,$J48)>0,1),0) -> 0 | M48: =IFERROR(IF(SEARCH(M$1,$J48)>0,1),0) -> 0 | N48: =IFERROR(IF(SEARCH(N$1,$J48)>0,1),0) -> 0 | O48: =SUM(K48:N48) -> 1 | P48: Diesel | Q48: 1000 | R48: 1480 | S48: =IFERROR(IF(Q48<>"",Q48,R48*0.7457),"Unknown") -> 1000 | T48: 44369 | U48: 385.00 | V48: 44764 | W48: 426.00 | X48: 41 | Y48: =X48*S48 -> 41000 | Z48: =IFERROR(INDEX(EFs!B:B,MATCH(P48,EFs!A:A,0))*Dataset!Y48/1000,0) -> 37.24411 | AA48: 32.875766 | AB48: -117.23955 | AC48: 1 | AD48: rooftop | AE48: 9500 | AF48: Gilman Dr | AI48: LA Jolla | AJ48: CA | AK48: San Diego County | AL48: 92093 | AM48: US | AN48: San Diego Geographic Information Source - JPA
A49: APCD2003-PTO-978673 | B49: Active | C49: 40025 | D49: [34C] Emergency Standby Engine | E49: Verizon Wireless | F49: Facility Manager | G49: 23945 Tecate Mission Rd Tecate, CA | H49: 91980 | I49: R | J49: EMERGENCY STANDBY ENGINE: GENERAL MOTORS ENGINE, FUELED WITH LIQUID PETROLEUM GAS, MODEL VORTEC 4.3 LITER, S/N 4.3L-15329, RATED AT 75 BHP, DRIVING A 45 KW GENERATOR. (978673-CCN-9/03) | K49: =IFERROR(IF(SEARCH(K$1,$J49)>0,1),0) -> 0 | L49: =IFERROR(IF(SEARCH(L$1,$J49)>0,1),0) -> 1 | M49: =IFERROR(IF(SEARCH(M$1,$J49)>0,1),0) -> 0 | N49: =IFERROR(IF(SEARCH(N$1,$J49)>0,1),0) -> 0 | O49: =SUM(K49:N49) -> 1 | P49: LPG | Q49: 45 | R49: 75 | S49: =IFERROR(IF(Q49<>"",Q49,R49*0.7457),"Unknown") -> 45 | T49: 44509 | U49: 643.10 | V49: 44509 | W49: 643.10 | X49: 0 | Y49: =X49*S49 -> 0 | Z49: =IFERROR(INDEX(EFs!B:B,MATCH(P49,EFs!A:A,0))*Dataset!Y49/1000,0) -> 0 | AA49: 32.578244 | AB49: -116.63041 | AC49: 1 | AD49: rooftop | AE49: 23945 | AF49: Tecate Mission Rd | AI49: Tecate | AJ49: CA | AK49: San Diego County | AL49: 91980 | AM49: US | AN49: San Diego Geographic Information Source - JPA
A50: APCD2003-PTO-978719 | B50: Active | C50: 40025 | D50: [34C] Emergency Standby Engine | E50: Verizon Wireless | F50: Project Manager | G50: 6020 Hughes St San Diego, CA | H50: 92115 | I50: J | J50: INTERNAL COMBUSTION ENGINE. MAKE: GENERAL MOTORS. MODEL: INDUSTRIAL POWER TRAIN VORTEC 4.3L. S/N 4.3L-15355. PROPANE FUELED. BHP= 68 HP. DRIVES AN ELECTRICAL EMERGENCY GENERATOR RATED AT: 45 KW. JFT28FEB03NEW | K50: =IFERROR(IF(SEARCH(K$1,$J50)>0,1),0) -> 0 | L50: =IFERROR(IF(SEARCH(L$1,$J50)>0,1),0) -> 0 | M50: =IFERROR(IF(SEARCH(M$1,$J50)>0,1),0) -> 0 | N50: =IFERROR(IF(SEARCH(N$1,$J50)>0,1),0) -> 1 | O50: =SUM(K50:N50) -> 1 | P50: Propane | Q50: 45 | R50: 68 | S50: =IFERROR(IF(Q50<>"",Q50,R50*0.7457),"Unknown") -> 45 | T50: 44334 | U50: 237.60 | V50: 44334 | W50: 237.60 | X50: 0 | Y50: =X50*S50 -> 0 | Z50: =IFERROR(INDEX(EFs!B:B,MATCH(P50,EFs!A:A,0))*Dataset!Y50/1000,0) -> 0 | AA50: 32.747343 | AB50: -117.06766 | AC50: 1 | AD50: rooftop | AE50: 6020 | AF50: Hughes St | AI50: San Diego | AJ50: CA | AK50: San Diego County | AL50: 92115 | AM50: US | AN50: San Diego Geographic Information Source - JPA
A51: APCD2003-PTO-979016 | B51: Active | C51: 40025 | D51: [34C] Emergency Standby Engine | E51: Albertsons #4786 | F51: Jill Washburn | G51: 1133 Mission Rd Fallbrook, CA | H51: 92028 | I51: A | J51: EMERGENCY STANDBY ENGINE: GENERAL MOTORS ENGINE, NATURAL GAS FUELED, MODEL INDUSTRIAL POWERTRAIN MODEL: VORTEC 4.3 LITER, S/N: 4.3L-14785, RATED AT 75 BHP, EQUIPPED WITH JOHNSON MATTHEY BANDITO CATALYTIC CONVERTER MODEL CX-4-4, DRIVING A 30 KW GENERATOR (MFR: KOHLER, MODEL: 30RZG, S/N 731682)(979016-CCN-9/03) | K51: =IFERROR(IF(SEARCH(K$1,$J51)>0,1),0) -> 0 | L51: =IFERROR(IF(SEARCH(L$1,$J51)>0,1),0) -> 0 | M51: =IFERROR(IF(SEARCH(M$1,$J51)>0,1),0) -> 1 | N51: =IFERROR(IF(SEARCH(N$1,$J51)>0,1),0) -> 0 | O51: =SUM(K51:N51) -> 1 | P51: Natural Gas | Q51: 30 | R51: 75 | S51: =IFERROR(IF(Q51<>"",Q51,R51*0.7457),"Unknown") -> 30 | T51: 44454 | U51: 601.90 | V51: 44454 | W51: 624.10 | X51: 22.2 | Y51: =X51*S51 -> 666 | Z51: =IFERROR(INDEX(EFs!B:B,MATCH(P51,EFs!A:A,0))*Dataset!Y51/1000,0) -> 0.48368631 | AA51: 33.386528 | AB51: -117.23905 | AC51: 0.9 | AD51: rooftop | AE51: 1133 | AF51: E Mission Rd | AI51: Fallbrook | AJ51: CA | AK51: San Diego County | AL51: 92028 | AM51: US | AN51: San Diego Geographic Information Source - JPA
A52: APCD2003-PTO-979115 | B52: Active | C52: 40025 | D52: [34W] Registered Engine (Rule 12) | E52: Scripps Mercy Hospital Chula Vista | F52: Rick Gorton | G52: 435 H St Chula Vista, CA | H52: 91910 | I52: Q | J52: INTERNAL COMBUSTION ENGINE. MAKE: CATERPILLAR. MODEL: 3508 DITA. SERIAL NO 23Z07288. BHP RATING: 1199 HP. DIESEL FUELED. DRIVES AN ELECTRICAL EMERGENCY GENERATOR RATED AT 800 KW. JFTFEB1403NEW EADSEP1906MOD | K52: =IFERROR(IF(SEARCH(K$1,$J52)>0,1),0) -> 1 | L52: =IFERROR(IF(SEARCH(L$1,$J52)>0,1),0) -> 0 | M52: =IFERROR(IF(SEARCH(M$1,$J52)>0,1),0) -> 0 | N52: =IFERROR(IF(SEARCH(N$1,$J52)>0,1),0) -> 0 | O52: =SUM(K52:N52) -> 1 | P52: Diesel | Q52: 800 | R52: 1199 | S52: =IFERROR(IF(Q52<>"",Q52,R52*0.7457),"Unknown") -> 800 | Y52: =X52*S52 -> 0 | Z52: =IFERROR(INDEX(EFs!B:B,MATCH(P52,EFs!A:A,0))*Dataset!Y52/1000,0) -> 0 | AA52: 32.633855 | AB52: -117.08321 | AC52: 1 | AD52: rooftop | AE52: 435 | AF52: H St | AI52: Chula Vista | AJ52: CA | AK52: San Diego County | AL52: 91910 | AM52: US | AN52: San Diego Geographic Information Source - JPA
A53: APCD2003-PTO-979211 | B53: Active | C53: 40025 | D53: [34W] Registered Engine (Rule 12) | E53: Coronado Shores Condominium Assn #3 | F53: General Manager | G53: 1760 Avenida Del Mundo Coronado, CA | H53: 92118 | I53: O | J53: EMERGENCY ENGINE: WAUKESHA, MODEL F817G, 227 BHP, NATURAL GAS, S/N 228946, DRIVING AN ONAN, MODEL 115 OWA, ELECTRIC GENERATOR. (979211 ALC 04/03) | K53: =IFERROR(IF(SEARCH(K$1,$J53)>0,1),0) -> 0 | L53: =IFERROR(IF(SEARCH(L$1,$J53)>0,1),0) -> 0 | M53: =IFERROR(IF(SEARCH(M$1,$J53)>0,1),0) -> 1 | N53: =IFERROR(IF(SEARCH(N$1,$J53)>0,1),0) -> 0 | O53: =SUM(K53:N53) -> 1 | P53: Natural Gas | R53: 227 | S53: =IFERROR(IF(Q53<>"",Q53,R53*0.7457),"Unknown") -> 169.2739 | T53: 44365 | U53: 640.30 | V53: 44750 | W53: 642.90 | X53: 2.6 | Y53: =X53*S53 -> 440.11214 | Z53: =IFERROR(INDEX(EFs!B:B,MATCH(P53,EFs!A:A,0))*Dataset!Y53/1000,0) -> 0.31963396 | AA53: 32.67686 | AB53: -117.17491 | AC53: 1 | AD53: rooftop | AE53: 1760 | AF53: Avenida Del Mundo | AI53: Coronado | AJ53: CA | AK53: San Diego County | AL53: 92118 | AM53: US | AN53: San Diego Geographic Information Source - JPA
A54: APCD2003-PTO-979218 | B54: Active | C54: 40025 | D54: [34H] California Certified Emergency Standby Engine | E54: Coronado Shores Condo Assn #4 | F54: Facility Manager | G54: 1770 Avenida Del Mundo Coronado, CA | H54: 92118 | I54: O | J54: Emergency Engine: Cummins, Model: QSJ8.9G, 205 BHP, NG fired, Engine Family No. KCEXB08.9ALB, S/N 74531735, Genset No. G190601854; equipped with an electronic air to fuel ratio controller, turbocharger, and engine block heater driving a 125-kW generator. | K54: =IFERROR(IF(SEARCH(K$1,$J54)>0,1),0) -> 0 | L54: =IFERROR(IF(SEARCH(L$1,$J54)>0,1),0) -> 0 | M54: =IFERROR(IF(SEARCH(M$1,$J54)>0,1),0) -> 0 | N54: =IFERROR(IF(SEARCH(N$1,$J54)>0,1),0) -> 0 | O54: =SUM(K54:N54) -> 0 | P54: Natural Gas | Q54: 125 | R54: 205 | S54: =IFERROR(IF(Q54<>"",Q54,R54*0.7457),"Unknown") -> 125 | T54: 44398 | U54: 20.60 | V54: 44756 | W54: 29.50 | X54: 8.9 | Y54: =X54*S54 -> 1112.5 | Z54: =IFERROR(INDEX(EFs!B:B,MATCH(P54,EFs!A:A,0))*Dataset!Y54/1000,0) -> 0.80795949 | AA54: 32.67686 | AB54: -117.17322 | AC54: 1 | AD54: rooftop | AE54: 1770 | AF54: Avenida Del Mundo | AI54: Coronado | AJ54: CA | AK54: San Diego County | AL54: 92118 | AM54: US | AN54: San Diego Geographic Information Source - JPA
A55: APCD2003-PTO-979449 | B55: Active | C55: 40025 | D55: [34C] Emergency Standby Engine | E55: Albertsons #710 | F55: Jill Washburn | G55: 8920 Fletcher Pkwy La Mesa, CA | H55: 91942 | I55: K | J55: EMERGENCY STANDBY ENGINE: GENERAL MOTORS ENGINE, NATURAL GAS FUELED, MODEL INDUSTRIAL POWERTRAIN VORTEC 4.3 LITER, S/N 12643, RATED AT 75 BHP, EQUIPPED WITH JOHNSON MATTHEY BANDITO CATALYTIC CONVERTER MODEL CX-4-4, DRIVING A 30 KW GENERATOR. (979449-CCN-9/03) | K55: =IFERROR(IF(SEARCH(K$1,$J55)>0,1),0) -> 0 | L55: =IFERROR(IF(SEARCH(L$1,$J55)>0,1),0) -> 0 | M55: =IFERROR(IF(SEARCH(M$1,$J55)>0,1),0) -> 1 | N55: =IFERROR(IF(SEARCH(N$1,$J55)>0,1),0) -> 0 | O55: =SUM(K55:N55) -> 1 | P55: Natural Gas | Q55: 30 | R55: 75 | S55: =IFERROR(IF(Q55<>"",Q55,R55*0.7457),"Unknown") -> 30 | T55: 44343 | U55: 207.70 | V55: 44764 | W55: 216.30 | X55: 8.6 | Y55: =X55*S55 -> 258 | Z55: =IFERROR(INDEX(EFs!B:B,MATCH(P55,EFs!A:A,0))*Dataset!Y55/1000,0) -> 0.18737398 | AA55: 32.785795 | AB55: -117.00535 | AC55: 1 | AD55: rooftop | AE55: 8920 | AF55: Fletcher Pkwy | AI55: LA Mesa | AJ55: CA | AK55: San Diego County | AL55: 91942 | AM55: US | AN55: Sandoval
A56: APCD2003-PTO-979451 | B56: Active | C56: 40025 | D56: [34C] Emergency Standby Engine | E56: El Super | F56: Rudy Hernandez | G56: 4421 University Ave San Diego, CA | H56: 92105 | I56: K | J56: EMERGENCY STANDBY ENGINE: GENERAL MOTORS ENGINE, NATURAL GAS FUELED, MODEL INDUSTRIAL POWERTRAIN VORTEC 4.3 LITER, S/N 4.3 L 11384, RATED AT 75 BHP, EQUIPPED WITH JOHNSON MATTHEY BANDITO CATALYTIC CONVERTER MODEL CX-4-4 DRIVING A 30 KW GENERATOR. (979451-CCN-9/03) | K56: =IFERROR(IF(SEARCH(K$1,$J56)>0,1),0) -> 0 | L56: =IFERROR(IF(SEARCH(L$1,$J56)>0,1),0) -> 0 | M56: =IFERROR(IF(SEARCH(M$1,$J56)>0,1),0) -> 1 | N56: =IFERROR(IF(SEARCH(N$1,$J56)>0,1),0) -> 0 | O56: =SUM(K56:N56) -> 1 | P56: Natural Gas | Q56: 30 | R56: 75 | S56: =IFERROR(IF(Q56<>"",Q56,R56*0.7457),"Unknown") -> 30 | T56: 44460 | U56: 236.00 | V56: 44460 | W56: 241.20 | X56: 5.2 | Y56: =X56*S56 -> 156 | Z56: =IFERROR(INDEX(EFs!B:B,MATCH(P56,EFs!A:A,0))*Dataset!Y56/1000,0) -> 0.11329589 | AA56: 32.748642 | AB56: -117.09922 | AC56: 1 | AD56: rooftop | AE56: 4421 | AF56: University Ave | AI56: San Diego | AJ56: CA | AK56: San Diego County | AL56: 92105 | AM56: US | AN56: San Diego Geographic Information Source - JPA
A57: APCD2003-PTO-979453 | B57: Active | C57: 40025 | D57: [34C] Emergency Standby Engine | E57: Albertsons #757 | F57: Jill Washburn | G57: 720 3rd Ave Chula Vista, CA | H57: 91910 | I57: Q | J57: EMERGENCY STANDBY ENGINE: GENERAL MOTORS ENGINE, NATURAL GAS FUELED, MODEL INDUSTRIAL POWERTRAIN VORTEC S/N 4.3-11483, RATED AT 75 BHP, EQUIPPED WITH JOHNSON MATTHEY BANDITO CATALYTIC CONVERTER MODEL CX-4-4, DRIVING A 30 KW GENERATOR. (979453-CCN-9/03) | K57: =IFERROR(IF(SEARCH(K$1,$J57)>0,1),0) -> 0 | L57: =IFERROR(IF(SEARCH(L$1,$J57)>0,1),0) -> 0 | M57: =IFERROR(IF(SEARCH(M$1,$J57)>0,1),0) -> 1 | N57: =IFERROR(IF(SEARCH(N$1,$J57)>0,1),0) -> 0 | O57: =SUM(K57:N57) -> 1 | P57: Natural Gas | Q57: 30 | R57: 75 | S57: =IFERROR(IF(Q57<>"",Q57,R57*0.7457),"Unknown") -> 30 | Y57: =X57*S57 -> 0 | Z57: =IFERROR(INDEX(EFs!B:B,MATCH(P57,EFs!A:A,0))*Dataset!Y57/1000,0) -> 0 | AA57: 32.62659 | AB57: -117.07523 | AC57: 1 | AD57: rooftop | AE57: 720 | AF57: 3rd Ave | AI57: Chula Vista | AJ57: CA | AK57: San Diego County | AL57: 91910 | AM57: US | AN57: San Diego Geographic Information Source - JPA
A58: APCD2003-PTO-979454 | B58: Active | C58: 40025 | D58: [34C] Emergency Standby Engine | E58: Albertsons #2783 | F58: Jill Washburn | G58: 2899 Jamacha Rd El Cajon, CA | H58: 92019 | I58: L | J58: EMERGENCY STANDBY ENGINE: GENERAL MOTORS ENGINE, NATURAL GAS FUELED, MODEL INDUSTRIAL POWERTRAIN VORTEC 4.3 LITER, S/N 707643, RATED AT 75 BHP, EQUIPPED WITH JOHNSON MATTHEY BANDITO CATALYTIC CONVERTER MODEL CX-4-4, DRIVING A 30 KW GENERATOR. (979454-CCN-9/03) | K58: =IFERROR(IF(SEARCH(K$1,$J58)>0,1),0) -> 0 | L58: =IFERROR(IF(SEARCH(L$1,$J58)>0,1),0) -> 0 | M58: =IFERROR(IF(SEARCH(M$1,$J58)>0,1),0) -> 1 | N58: =IFERROR(IF(SEARCH(N$1,$J58)>0,1),0) -> 0 | O58: =SUM(K58:N58) -> 1 | P58: Natural Gas | Q58: 30 | R58: 75 | S58: =IFERROR(IF(Q58<>"",Q58,R58*0.7457),"Unknown") -> 30 | T58: 44713 | U58: 314.70 | V58: 44713 | W58: 322.50 | X58: 7.8 | Y58: =X58*S58 -> 234 | Z58: =IFERROR(INDEX(EFs!B:B,MATCH(P58,EFs!A:A,0))*Dataset!Y58/1000,0) -> 0.16994384 | AA58: 32.739871 | AB58: -116.93809 | AC58: 1 | AD58: rooftop | AE58: 2899 | AF58: Jamacha Rd | AI58: El Cajon | AJ58: CA | AK58: San Diego County | AL58: 92019 | AM58: US | AN58: San Diego Geographic Information Source - JPA
A59: APCD2003-PTO-979455 | B59: Active | C59: 40025 | D59: [34C] Emergency Standby Engine | E59: Albertsons #723 | F59: Jill Washburn | G59: 9831 Campo Rd Spring Valley, CA | H59: 91977 | I59: K | J59: EMERGENCY STANDBY ENGINE: GENERAL MOTORS ENGINE, NATURAL GAS FUELED, MODEL INDUSTRIAL POWERTRAIN VORTEC 4.3 LITER, S/N 4.3 L-12642, RATED AT 75 BHP, EQUIPPED WITH JOHNSON MATTHEY BANDITO CATALYTIC CONVERTER MODEL CX-4-4, DRIVING A 30 KW GENERATOR (S/N 707684). _x000D_(979455-CCN-9/03) | K59: =IFERROR(IF(SEARCH(K$1,$J59)>0,1),0) -> 0 | L59: =IFERROR(IF(SEARCH(L$1,$J59)>0,1),0) -> 0 | M59: =IFERROR(IF(SEARCH(M$1,$J59)>0,1),0) -> 1 | N59: =IFERROR(IF(SEARCH(N$1,$J59)>0,1),0) -> 0 | O59: =SUM(K59:N59) -> 1 | P59: Natural Gas | Q59: 30 | R59: 75 | S59: =IFERROR(IF(Q59<>"",Q59,R59*0.7457),"Unknown") -> 30 | T59: 44439 | U59: 210.70 | V59: 44768 | W59: 226.10 | X59: 15.4 | Y59: =X59*S59 -> 462 | Z59: =IFERROR(INDEX(EFs!B:B,MATCH(P59,EFs!A:A,0))*Dataset!Y59/1000,0) -> 0.33553014 | AA59: 32.747011 | AB59: -116.98408 | AC59: 1 | AD59: rooftop | AE59: 9831 | AF59: Campo Rd | AI59: Spring Valley | AJ59: CA | AK59: San Diego County | AL59: 91977 | AM59: US | AN59: San Diego Geographic Information Source - JPA
A60: APCD2003-PTO-979456 | B60: Active | C60: 40025 | D60: [34C] Emergency Standby Engine | E60: Albertsons #711 | F60: Jill Washburn | G60: 1929 W San Marcos San Marcos, CA | H60: 92078 | I60: E | J60: EMERGENCY STANDBY ENGINE: GENERAL MOTORS ENGINE, NATURAL GAS FUELED, MODEL INDUSTRIAL POWERTRAIN VORTEC 4.3 LITER, S/N 707099, RATED AT 75 BHP, EQUIPPED WITH JOHNSON MATTHEY BANDITO CATALYTIC CONVERTER MODEL CX-4-4, DRIVING A 30 KW GENERATOR. (979456-CCN-9/03) | K60: =IFERROR(IF(SEARCH(K$1,$J60)>0,1),0) -> 0 | L60: =IFERROR(IF(SEARCH(L$1,$J60)>0,1),0) -> 0 | M60: =IFERROR(IF(SEARCH(M$1,$J60)>0,1),0) -> 1 | N60: =IFERROR(IF(SEARCH(N$1,$J60)>0,1),0) -> 0 | O60: =SUM(K60:N60) -> 1 | P60: Natural Gas | Q60: 30 | R60: 75 | S60: =IFERROR(IF(Q60<>"",Q60,R60*0.7457),"Unknown") -> 30 | Y60: =X60*S60 -> 0 | Z60: =IFERROR(INDEX(EFs!B:B,MATCH(P60,EFs!A:A,0))*Dataset!Y60/1000,0) -> 0 | AA60: 33.131646 | AB60: -117.21063 | AC60: 1 | AD60: rooftop | AE60: 1929 | AF60: W San Marcos Blvd W | AI60: San Marcos | AJ60: CA | AK60: San Diego County | AL60: 92078 | AM60: US | AN60: San Diego Geographic Information Source - JPA
A61: APCD2003-PTO-979460 | B61: Active | C61: 40025 | D61: [34H] California Certified Emergency Standby Engine | E61: Borrego Springs Fire Protect Dist | F61: Fire Chief Dept | G61: 2324 Stirrup Rd Borrego Springs, CA | H61: 92004 | I61: D | J61: INTERNAL COMBUSTION ENGINE, Mfr: John Deere, Model: 6068HF150, Serial: PE6068H228212, Family: 2JDXL06.8012, BHP RATING: 251 BHP, DIESEL FUELED, EQUIPPED WITH A TURBOCHARGER AND AN AFTERCOOLER. DRIVES AN ELECTRICAL EMERGENCY GENERATOR RATED AT 150 KW. | K61: =IFERROR(IF(SEARCH(K$1,$J61)>0,1),0) -> 1 | L61: =IFERROR(IF(SEARCH(L$1,$J61)>0,1),0) -> 0 | M61: =IFERROR(IF(SEARCH(M$1,$J61)>0,1),0) -> 0 | N61: =IFERROR(IF(SEARCH(N$1,$J61)>0,1),0) -> 0 | O61: =SUM(K61:N61) -> 1 | P61: Diesel | Q61: 150 | R61: 251 | S61: =IFERROR(IF(Q61<>"",Q61,R61*0.7457),"Unknown") -> 150 | T61: 44561 | U61: 543.70 | V61: 44589 | W61: 572.60 | X61: 28.9 | Y61: =X61*S61 -> 4335 | Z61: =IFERROR(INDEX(EFs!B:B,MATCH(P61,EFs!A:A,0))*Dataset!Y61/1000,0) -> 3.9378833 | AA61: 33.261553 | AB61: -116.37196 | AC61: 1 | AD61: rooftop | AE61: 2324 | AF61: Stirrup Rd | AI61: Borrego Springs | AJ61: CA | AK61: San Diego County | AL61: 92004 | AM61: US | AN61: San Diego Geographic Information Source - JPA
A62: APCD2003-PTO-980022 | B62: Active | C62: 40025 | D62: [34W] Registered Engine (Rule 12) | E62: Southwestern Community College | F62: Travis Rayburn | G62: Maintenance Department,900 Otay Lakes Road Chula Vista, CA | H62: 91910 | I62: Q | J62: EMERGENCY ENGINE GENERATOR, 50 HP FORD NATURAL GAS ENGINE, MODEL CSG-649I-6005-F S/N: 28800-1-04-98 APPL# 980022 EFH 10/03 | K62: =IFERROR(IF(SEARCH(K$1,$J62)>0,1),0) -> 0 | L62: =IFERROR(IF(SEARCH(L$1,$J62)>0,1),0) -> 0 | M62: =IFERROR(IF(SEARCH(M$1,$J62)>0,1),0) -> 1 | N62: =IFERROR(IF(SEARCH(N$1,$J62)>0,1),0) -> 0 | O62: =SUM(K62:N62) -> 1 | P62: Natural Gas | R62: 50 | S62: =IFERROR(IF(Q62<>"",Q62,R62*0.7457),"Unknown") -> 37.285 | T62: 44561 | U62: 397.50 | V62: 44602 | W62: 403.90 | X62: 6.4 | Y62: =X62*S62 -> 238.624 | Z62: =IFERROR(INDEX(EFs!B:B,MATCH(P62,EFs!A:A,0))*Dataset!Y62/1000,0) -> 0.17330204 | AA62: 32.640533 | AB62: -116.99837 | AC62: 1 | AD62: rooftop | AE62: 900 | AF62: Otay Lakes Rd | AI62: Chula Vista | AJ62: CA | AK62: San Diego County | AL62: 91910 | AM62: US | AN62: San Diego Geographic Information Source - JPA
A63: APCD2004-PTO-961839 | B63: Active | C63: 40025 | D63: [34W] Registered Engine (Rule 12) | E63: Crestwood San Diego | F63: Rafael Diaz | G63: 5550 University Ave San Diego, CA | H63: 92105 | I63: K | J63: EMERGENCY STANDBY ENGINE, FORD MODEL 300GF, 107 HP, S/N 0973704224, NATURAL GAS FIRED. APPL# 961839 EFH 12/98 (981164 4/04) | K63: =IFERROR(IF(SEARCH(K$1,$J63)>0,1),0) -> 0 | L63: =IFERROR(IF(SEARCH(L$1,$J63)>0,1),0) -> 0 | M63: =IFERROR(IF(SEARCH(M$1,$J63)>0,1),0) -> 1 | N63: =IFERROR(IF(SEARCH(N$1,$J63)>0,1),0) -> 0 | O63: =SUM(K63:N63) -> 1 | P63: Natural Gas | R63: 107 | S63: =IFERROR(IF(Q63<>"",Q63,R63*0.7457),"Unknown") -> 79.7899 | T63: 44399 | U63: 1251.80 | V63: 44763 | W63: 1284.50 | X63: 32.7 | Y63: =X63*S63 -> 2609.1297 | Z63: =IFERROR(INDEX(EFs!B:B,MATCH(P63,EFs!A:A,0))*Dataset!Y63/1000,0) -> 1.8948954 | AA63: 32.749508 | AB63: -117.0766 | AC63: 1 | AD63: rooftop | AE63: 5550 | AF63: University Ave | AI63: San Diego | AJ63: CA | AK63: San Diego County | AL63: 92105 | AM63: US | AN63: San Diego Geographic Information Source - JPA
A64: APCD2004-PTO-976447 | B64: Active | C64: 40025 | D64: [34W] Registered Engine (Rule 12) | E64: SDG&E | F64: Facility Manager | G64: 21945 Crestline Rd Palomar Mountain, CA | H64: 92060 | I64: B | J64: EMERGENCY ENGINE GENERATOR, 82 HP FORD ENGINE, MODEL CGS-649-6005-F, PROPANE FIRED S/N 24379F-27-RC. APPL# 976447 EFH 10/02 | K64: =IFERROR(IF(SEARCH(K$1,$J64)>0,1),0) -> 0 | L64: =IFERROR(IF(SEARCH(L$1,$J64)>0,1),0) -> 0 | M64: =IFERROR(IF(SEARCH(M$1,$J64)>0,1),0) -> 0 | N64: =IFERROR(IF(SEARCH(N$1,$J64)>0,1),0) -> 1 | O64: =SUM(K64:N64) -> 1 | P64: Propane | R64: 82 | S64: =IFERROR(IF(Q64<>"",Q64,R64*0.7457),"Unknown") -> 61.1474 | T64: 44455 | U64: 1394.50 | V64: 44763 | W64: 1477.50 | X64: 83 | Y64: =X64*S64 -> 5075.2342 | Z64: =IFERROR(INDEX(EFs!B:B,MATCH(P64,EFs!A:A,0))*Dataset!Y64/1000,0) -> 4.1814855 | AA64: 33.309078 | AB64: -116.85508 | AC64: 1 | AD64: rooftop | AE64: 21945 | AF64: Crestline Rd | AI64: Palomar Mountain | AJ64: CA | AK64: San Diego County | AL64: 92060 | AM64: US | AN64: San Diego Geographic Information Source - JPA
A65: APCD2004-PTO-977637 | B65: Active | C65: 40025 | D65: [34C] Emergency Standby Engine | E65: Palomar College | F65: Facility Manager | G65: 1140 W Mission Rd San Marcos, CA | H65: 92069 | I65: B | J65: INTERNAL COMBUSTION ENGINE. NATURAL GAS FUELED. MAKE: CUMMINS. MODEL: GTA-855G2. SERIAL NO.: 25272444. TURBOCHARGED AND AFTERCOOLED. EQUIPPED WITH A 3 WAY REDUCTION CATALYST AND A NEUTRONICS MARK IV AIR TO FUEL RATIO CONTROLLER. IT POWERS AN ELECTRICAL EMERGENCY GENERATOR RATED AT 215 KW. | K65: =IFERROR(IF(SEARCH(K$1,$J65)>0,1),0) -> 0 | L65: =IFERROR(IF(SEARCH(L$1,$J65)>0,1),0) -> 0 | M65: =IFERROR(IF(SEARCH(M$1,$J65)>0,1),0) -> 1 | N65: =IFERROR(IF(SEARCH(N$1,$J65)>0,1),0) -> 0 | O65: =SUM(K65:N65) -> 1 | P65: Natural Gas | Q65: 215 | R65: Unknown | S65: =IFERROR(IF(Q65<>"",Q65,R65*0.7457),"Unknown") -> 215 | T65: 44621 | U65: 414.30 | V65: 44621 | W65: 415.30 | X65: 1 | Y65: =X65*S65 -> 215 | Z65: =IFERROR(INDEX(EFs!B:B,MATCH(P65,EFs!A:A,0))*Dataset!Y65/1000,0) -> 0.15614498 | AA65: 33.152442 | AB65: -117.17878 | AC65: 1 | AD65: rooftop | AE65: 1140 | AF65: W Mission Rd W | AI65: San Marcos | AJ65: CA | AK65: San Diego County | AL65: 92069 | AM65: US | AN65: San Diego Geographic Information Source - JPA
A66: APCD2004-PTO-978748 | B66: Active | C66: 40025 | D66: [34C] Emergency Standby Engine | E66: DIRECTED ELECTRONICS | G66: 1 VIPER WY VISTA, CA | H66: 92081 | I66: B | J66: EMERGENCY STANDBY ENGINE, GENERAL MOTORS ENGINE, FUELED WITH NATURAL GAS, MODEL 4.3 LITER, S/N 101LXT011300976, RATED AT 64 BHP, DRIVING A 40 KW APPL # 978748 EFH 04/04 | K66: =IFERROR(IF(SEARCH(K$1,$J66)>0,1),0) -> 0 | L66: =IFERROR(IF(SEARCH(L$1,$J66)>0,1),0) -> 0 | M66: =IFERROR(IF(SEARCH(M$1,$J66)>0,1),0) -> 1 | N66: =IFERROR(IF(SEARCH(N$1,$J66)>0,1),0) -> 0 | O66: =SUM(K66:N66) -> 1 | P66: Natural Gas | Q66: 40 | R66: 64 | S66: =IFERROR(IF(Q66<>"",Q66,R66*0.7457),"Unknown") -> 40 | T66: 44621 | U66: 0.00 | V66: 44621 | W66: 0.00 | X66: 0 | Y66: =X66*S66 -> 0 | Z66: =IFERROR(INDEX(EFs!B:B,MATCH(P66,EFs!A:A,0))*Dataset!Y66/1000,0) -> 0 | AA66: 33.155386 | AB66: -117.21916 | AC66: 1 | AD66: rooftop | AE66: 1 | AF66: Viper Way | AI66: Vista | AJ66: CA | AK66: San Diego County | AL66: 92081 | AM66: US | AN66: San Diego Geographic Information Source - JPA
A67: APCD2004-PTO-978795 | B67: Active | C67: 40025 | D67: [34C] Emergency Standby Engine | E67: Federal Aviation Administration (JLI RCAG) | F67: SAN SSC ENV Manager (JLI RCAG) | G67: FAA JLI RCAG Volcan Mtn Julian, CA | H67: 92036 | I67: D | J67: EMERGENCY STANDBY ENGINE: GENERAL MOTORS ENGINE, FUELED WITH LIQUID PETROLEUM GAS, MODEL INDUSTRIAL POWER TRAIN VORTEC 4.3 LITER, S/N 4.3L-15008 RATED AT 72 BHP, DRIVING A 40 KW GENERATOR. | K67: =IFERROR(IF(SEARCH(K$1,$J67)>0,1),0) -> 0 | L67: =IFERROR(IF(SEARCH(L$1,$J67)>0,1),0) -> 1 | M67: =IFERROR(IF(SEARCH(M$1,$J67)>0,1),0) -> 0 | N67: =IFERROR(IF(SEARCH(N$1,$J67)>0,1),0) -> 0 | O67: =SUM(K67:N67) -> 1 | P67: LPG | Q67: 40 | R67: 72 | S67: =IFERROR(IF(Q67<>"",Q67,R67*0.7457),"Unknown") -> 40 | T67: 44561 | U67: 2140.80 | V67: 44700 | W67: 2429.20 | X67: 288.4 | Y67: =X67*S67 -> 11536 | Z67: =IFERROR(INDEX(EFs!B:B,MATCH(P67,EFs!A:A,0))*Dataset!Y67/1000,0) -> 11.451968 | AA67: 33.07347 | AB67: -116.58901 | AC67: 1 | AD67: place | AI67: Julian | AJ67: CA | AK67: San Diego County | AL67: 92036 | AM67: US | AN67: TIGER/LineÂ® dataset from the US Census Bureau
A68: APCD2004-PTO-978862 | B68: Active | C68: 40025 | D68: [34C] Emergency Standby Engine | E68: Albertsons #738 | F68: Jill Washburn | G68: 9560 Winter Gardens Blvd San Diego, CA | H68: 92040 | I68: H | J68: EMERGENCY STANDBY ENGINE: GENERAL MOTORS ENGINE, FUELED WITH NATURAL GAS, MODEL INDUSTRIAL POWER TRAIN VORTEC 4.3 LITER, S/N 4.3L-15514, RATED AT 75 BHP, EQUIPPED WITH JOHNSON MATTHEY BANDITO CATALYTIC CONVERTER, MODEL CX-4-4, DRIVING A 30 KW GENERATOR. (978862-CCN-1/04) | K68: =IFERROR(IF(SEARCH(K$1,$J68)>0,1),0) -> 0 | L68: =IFERROR(IF(SEARCH(L$1,$J68)>0,1),0) -> 0 | M68: =IFERROR(IF(SEARCH(M$1,$J68)>0,1),0) -> 1 | N68: =IFERROR(IF(SEARCH(N$1,$J68)>0,1),0) -> 0 | O68: =SUM(K68:N68) -> 1 | P68: Natural Gas | Q68: 30 | R68: 75 | S68: =IFERROR(IF(Q68<>"",Q68,R68*0.7457),"Unknown") -> 30 | Y68: =X68*S68 -> 0 | Z68: =IFERROR(INDEX(EFs!B:B,MATCH(P68,EFs!A:A,0))*Dataset!Y68/1000,0) -> 0 | AA68: 32.851525 | AB68: -116.93213 | AC68: 0.9 | AD68: rooftop | AE68: 9560 | AF68: Winter Gardens Blvd | AI68: Lakeside | AJ68: CA | AK68: San Diego County | AL68: 92040 | AM68: US | AN68: San Diego Geographic Information Source - JPA
A69: APCD2004-PTO-978902 | B69: Active | C69: 40025 | D69: [34C] Emergency Standby Engine | E69: Target Store T1815 | F69: Team Leader | G69: 910 Eastlake Pkwy Chula Vista, CA | H69: 91915 | I69: R | J69: EMERGENCY STANDBY ENGINE: FORD ENGINE, FUELED WITH NATURAL GAS, MODEL ESG-642I-6005-A, S/N 02-09-015909, RATED AT 57 BHP, MANUFACTURE YEAR: DECEMBER 2002. EQUIPPED WITH THREE-WAY CATALYTIC CONVERTER AND AIR TO FUEL RADIO CONTROLLER, DRIVING A 35 KW GENERATOR.(978902-CCN-3/04) | K69: =IFERROR(IF(SEARCH(K$1,$J69)>0,1),0) -> 0 | L69: =IFERROR(IF(SEARCH(L$1,$J69)>0,1),0) -> 0 | M69: =IFERROR(IF(SEARCH(M$1,$J69)>0,1),0) -> 1 | N69: =IFERROR(IF(SEARCH(N$1,$J69)>0,1),0) -> 0 | O69: =SUM(K69:N69) -> 1 | P69: Natural Gas | Q69: 35 | R69: 57 | S69: =IFERROR(IF(Q69<>"",Q69,R69*0.7457),"Unknown") -> 35 | T69: 44364 | U69: 140.60 | V69: 44725 | W69: 147.50 | X69: 6.9 | Y69: =X69*S69 -> 241.5 | Z69: =IFERROR(INDEX(EFs!B:B,MATCH(P69,EFs!A:A,0))*Dataset!Y69/1000,0) -> 0.17539076 | AA69: 32.650405 | AB69: -116.96766 | AC69: 1 | AD69: rooftop | AE69: 910 | AF69: Eastlake Pkwy | AI69: Chula Vista | AJ69: CA | AK69: San Diego County | AL69: 91914 | AM69: US | AN69: Sandoval
A70: APCD2004-PTO-979519 | B70: Active | C70: 40025 | D70: [34C] Emergency Standby Engine | E70: North County Transit District | F70: Stacey Coppess | G70: 235 S Tremont Av Oceanside, CA | H70: 92054 | I70: C | J70: EMERGENCY STANDBY ENGINE: GENERAL MOTORS ENGINE, FUELED WITH NATURAL GAS, MODEL INDUSTRIAL POWER TRAIN VORTEC 4.3 LITER, S/N: 4.3L-16209, RATED AT 60 BHP, DRIVING A 35 KW GENERATOR. (979519-CCN-12/03) | K70: =IFERROR(IF(SEARCH(K$1,$J70)>0,1),0) -> 0 | L70: =IFERROR(IF(SEARCH(L$1,$J70)>0,1),0) -> 0 | M70: =IFERROR(IF(SEARCH(M$1,$J70)>0,1),0) -> 1 | N70: =IFERROR(IF(SEARCH(N$1,$J70)>0,1),0) -> 0 | O70: =SUM(K70:N70) -> 1 | P70: Natural Gas | Q70: 35 | R70: 60 | S70: =IFERROR(IF(Q70<>"",Q70,R70*0.7457),"Unknown") -> 35 | T70: 44421 | U70: 378.70 | V70: 44783 | W70: 428.30 | X70: 49.6 | Y70: =X70*S70 -> 1736 | Z70: =IFERROR(INDEX(EFs!B:B,MATCH(P70,EFs!A:A,0))*Dataset!Y70/1000,0) -> 1.2607799 | AA70: 33.192986 | AB70: -117.37849 | AC70: 1 | AD70: range_interpolation | AE70: 235 | AF70: S Tremont St | AI70: Oceanside | AJ70: CA | AK70: San Diego County | AL70: 92054 | AM70: US | AN70: TIGER/LineÂ® dataset from the US Census Bureau
A71: APCD2004-PTO-979720 | B71: Active | C71: 40025 | D71: [34C] Emergency Standby Engine | E71: Albertsons #740 | F71: Jill Washburn | G71: 4150 Oceanside Blvd Oceanside, CA | H71: 92056 | I71: C | J71: EMERGENCY STANDBY ENGINE: GENERAL MOTORS ENGINE, FUELED WITH NATURAL GAS, MODEL GM-4.3L, S/N 4.3L-12665; INDUSTRIAL POWER TRAIN VORTEC 4.3 LITER, RATED AT 75 BHP, EQUIPPED WITH JOHNSON MATTHEY BANDITO CATALYTIC CONVERTER MODEL CX-4-4, DRIVING A 30 KW GENERATOR. (979720-CCN-1/04) | K71: =IFERROR(IF(SEARCH(K$1,$J71)>0,1),0) -> 0 | L71: =IFERROR(IF(SEARCH(L$1,$J71)>0,1),0) -> 0 | M71: =IFERROR(IF(SEARCH(M$1,$J71)>0,1),0) -> 1 | N71: =IFERROR(IF(SEARCH(N$1,$J71)>0,1),0) -> 0 | O71: =SUM(K71:N71) -> 1 | P71: Natural Gas | Q71: 30 | R71: 75 | S71: =IFERROR(IF(Q71<>"",Q71,R71*0.7457),"Unknown") -> 30 | T71: 44559 | U71: 284.50 | V71: 44743 | W71: 361.10 | X71: 76.6 | Y71: =X71*S71 -> 2298 | Z71: =IFERROR(INDEX(EFs!B:B,MATCH(P71,EFs!A:A,0))*Dataset!Y71/1000,0) -> 1.6689356 | AA71: 33.207748 | AB71: -117.28733 | AC71: 1 | AD71: rooftop | AE71: 4150 | AF71: Oceanside Blvd | AI71: Oceanside | AJ71: CA | AK71: San Diego County | AL71: 92056 | AM71: US | AN71: San Diego Geographic Information Source - JPA
A72: APCD2004-PTO-979721 | B72: Active | C72: 40025 | D72: [34C] Emergency Standby Engine | E72: Albertsons #758 | F72: Jill Washburn | G72: 543 Sweetwater Rd Spring Valley, CA | H72: 91977 | I72: K | J72: EMERGENCY STANDBY ENGINE: GENERAL MOTORS ENGINE, FUELED WITH NATURAL GAS, MODEL INDUSTRIAL POWER TRAIN VORTEC 4.3 LITER, S/N 4.3L-11529, RATED AT 75 BHP, EQUIPPED WITH JOHNSON MATTHEY BANDITO CATALYTIC CONVERTER MODEL CX-4-4, DRIVING A 30 KW GENERATOR (S/N 707006). _x000D_(979721-CCN-1/04) | K72: =IFERROR(IF(SEARCH(K$1,$J72)>0,1),0) -> 0 | L72: =IFERROR(IF(SEARCH(L$1,$J72)>0,1),0) -> 0 | M72: =IFERROR(IF(SEARCH(M$1,$J72)>0,1),0) -> 1 | N72: =IFERROR(IF(SEARCH(N$1,$J72)>0,1),0) -> 0 | O72: =SUM(K72:N72) -> 1 | P72: Natural Gas | Q72: 30 | R72: 75 | S72: =IFERROR(IF(Q72<>"",Q72,R72*0.7457),"Unknown") -> 30 | T72: 44439 | U72: 23.10 | V72: 44782 | W72: 39.20 | X72: 16.1 | Y72: =X72*S72 -> 483 | Z72: =IFERROR(INDEX(EFs!B:B,MATCH(P72,EFs!A:A,0))*Dataset!Y72/1000,0) -> 0.35078151 | AA72: 32.708059 | AB72: -117.00869 | AC72: 1 | AD72: rooftop | AE72: 543 | AF72: Sweetwater Rd | AI72: Spring Valley | AJ72: CA | AK72: San Diego County | AL72: 91977 | AM72: US | AN72: San Diego Geographic Information Source - JPA
A73: APCD2004-PTO-979731 | B73: Active | C73: 40025 | D73: [34W] Registered Engine (Rule 12) | E73: Rainbow Municipal Water District | F73: Jeff Stacy | G73: 3707 Old Hy 395 Fallbrook, CA | H73: 92028 | I73: A | J73: EMERGENCY ENGINE: MFR: GENERAC, CONFIGURATION: V-8, DISPLACEMENT: 5.0 LITER, S/N 75872_x000D_FUEL: PROPANE, 70 HP FOR A GENERATOR (MFR: GENERAC, MODEL: 92A02209-S, S/N 2003351) SEWAGE LIFT STATION #3 APPL# 979731 EFH 07/03 | K73: =IFERROR(IF(SEARCH(K$1,$J73)>0,1),0) -> 0 | L73: =IFERROR(IF(SEARCH(L$1,$J73)>0,1),0) -> 0 | M73: =IFERROR(IF(SEARCH(M$1,$J73)>0,1),0) -> 0 | N73: =IFERROR(IF(SEARCH(N$1,$J73)>0,1),0) -> 1 | O73: =SUM(K73:N73) -> 1 | P73: Propane | R73: 70 | S73: =IFERROR(IF(Q73<>"",Q73,R73*0.7457),"Unknown") -> 52.199 | T73: 44561 | U73: 730.40 | V73: 44617 | W73: 748.60 | X73: 18.2 | Y73: =X73*S73 -> 950.0218 | Z73: =IFERROR(INDEX(EFs!B:B,MATCH(P73,EFs!A:A,0))*Dataset!Y73/1000,0) -> 0.78272296 | AA73: 33.382832 | AB73: -117.22068 | AC73: 0.6 | AD73: street_center | AF73: Old Hill Rd | AI73: Fallbrook | AJ73: CA | AK73: San Diego County | AL73: 92028 | AM73: US | AN73: TIGER/LineÂ® dataset from the US Census Bureau
A74: APCD2004-PTO-980136 | B74: Active | C74: 40025 | D74: [34C] Emergency Standby Engine | E74: Albertsons #707 | F74: Dean Fredrickson | G74: 7090 Broadway Lemon Grove, CA | H74: 91945 | I74: N | J74: EMERGENCY ENGINE: GENERAL MOTORS, MODEL INDUSTRIAL POWERTRAIN VORTEC 4.3L, 4-CYCLE, 75 BHP, NATURAL GAS FIRED, S/N 709398, WITH A JOHNSON MATTHEY MODEL CX-4-4 CATALYTIC CONVERTER, DRIVING A 30-KW KOHLER GENERATOR. (980136 ALC 04/04) | K74: =IFERROR(IF(SEARCH(K$1,$J74)>0,1),0) -> 0 | L74: =IFERROR(IF(SEARCH(L$1,$J74)>0,1),0) -> 0 | M74: =IFERROR(IF(SEARCH(M$1,$J74)>0,1),0) -> 1 | N74: =IFERROR(IF(SEARCH(N$1,$J74)>0,1),0) -> 0 | O74: =SUM(K74:N74) -> 1 | P74: Natural Gas | Q74: 30 | R74: 75 | S74: =IFERROR(IF(Q74<>"",Q74,R74*0.7457),"Unknown") -> 30 | T74: 44669 | U74: 474.30 | V74: 44669 | W74: 480.40 | X74: 6.1 | Y74: =X74*S74 -> 183 | Z74: =IFERROR(INDEX(EFs!B:B,MATCH(P74,EFs!A:A,0))*Dataset!Y74/1000,0) -> 0.1329048 | AA74: 32.742683 | AB74: -117.04397 | AC74: 1 | AD74: range_interpolation | AE74: 7090 | AF74: Broadway | AI74: Lemon Grove | AJ74: CA | AK74: San Diego County | AL74: 91945 | AM74: US | AN74: TIGER/LineÂ® dataset from the US Census Bureau
A75: APCD2004-PTO-980239 | B75: Active | C75: 40025 | D75: [34W] Registered Engine (Rule 12) | E75: Albertsons #708 | F75: Jill Washburn | G75: 151 Woodland Pkwy San Marcos, CA | H75: 92069 | I75: B | J75: INTERNAL COMBUSTION EMERGENCY STANDBY ENGINE: 50 HP (82 HP MAX CONT. RATING), FORD MODEL CSG-6491-6005-F, S/N 07278, PROPANE FIRED, DRIVING A 30 KW KOHLER MODEL 30RZ82 GENERATOR, S/N 376427980239 EAD 1/16/04 | K75: =IFERROR(IF(SEARCH(K$1,$J75)>0,1),0) -> 0 | L75: =IFERROR(IF(SEARCH(L$1,$J75)>0,1),0) -> 0 | M75: =IFERROR(IF(SEARCH(M$1,$J75)>0,1),0) -> 0 | N75: =IFERROR(IF(SEARCH(N$1,$J75)>0,1),0) -> 1 | O75: =SUM(K75:N75) -> 1 | P75: Propane | Q75: 30 | R75: 50 | S75: =IFERROR(IF(Q75<>"",Q75,R75*0.7457),"Unknown") -> 30 | T75: 44593 | U75: 809.60 | V75: 44593 | W75: 812.50 | X75: 2.9 | Y75: =X75*S75 -> 87 | Z75: =IFERROR(INDEX(EFs!B:B,MATCH(P75,EFs!A:A,0))*Dataset!Y75/1000,0) -> 0.0716793 | AA75: 33.139847 | AB75: -117.13848 | AC75: 1 | AD75: rooftop | AE75: 151 | AF75: Woodland Pkwy | AI75: San Marcos | AJ75: CA | AK75: San Diego County | AL75: 92069 | AM75: US | AN75: Sandoval
A76: APCD2004-PTO-980290 | B76: Active | C76: 40025 | D76: [34W] Registered Engine (Rule 12) | E76: Target Corporation | F76: Steve Musser | G76: 1240 Broadway Chula Vista, CA | H76: 91911 | I76: R | J76: INTERNAL COMBUSTION ENGINE. MAKE: FORD. MODEL: CSG-6491-6005-A. SERIAL NO.: 03576 B-27-RC. BHP RATING: 62 HP. NATURAL GAS OR PROPANE FUELED. DRIVES AN ELECTRICAL EMERGENCY GENERATOR BRAND ONAN. JFT NEW FEB1804 | K76: =IFERROR(IF(SEARCH(K$1,$J76)>0,1),0) -> 0 | L76: =IFERROR(IF(SEARCH(L$1,$J76)>0,1),0) -> 0 | M76: =IFERROR(IF(SEARCH(M$1,$J76)>0,1),0) -> 1 | N76: =IFERROR(IF(SEARCH(N$1,$J76)>0,1),0) -> 1 | O76: =SUM(K76:N76) -> 2 | P76: Natural Gas | R76: 62 | S76: =IFERROR(IF(Q76<>"",Q76,R76*0.7457),"Unknown") -> 46.2334 | T76: 44363 | U76: 315.70 | V76: 44718 | W76: 326.20 | X76: 10.5 | Y76: =X76*S76 -> 485.4507 | Z76: =IFERROR(INDEX(EFs!B:B,MATCH(P76,EFs!A:A,0))*Dataset!Y76/1000,0) -> 0.35256135 | AA76: 32.604726 | AB76: -117.08095 | AC76: 1 | AD76: rooftop | AE76: 1240 | AF76: Broadway | AI76: Chula Vista | AJ76: CA | AK76: San Diego County | AL76: 91911 | AM76: US | AN76: San Diego Geographic Information Source - JPA
A77: APCD2004-PTO-980292 | B77: Active | C77: 40025 | D77: [34W] Registered Engine (Rule 12) | E77: Target T1029 | F77: General Manager | G77: 1010 El Camino Real N Encinitas, CA | H77: 92024 | I77: E | J77: EMERGENCY ENGINE: FORD, MODEL CSG-6491-6005-A, 62 BHP, NATURAL GAS AND PROPANE FIRED, S/N 23302 F-13-RC. (980292 ALC 11/03) | K77: =IFERROR(IF(SEARCH(K$1,$J77)>0,1),0) -> 0 | L77: =IFERROR(IF(SEARCH(L$1,$J77)>0,1),0) -> 0 | M77: =IFERROR(IF(SEARCH(M$1,$J77)>0,1),0) -> 1 | N77: =IFERROR(IF(SEARCH(N$1,$J77)>0,1),0) -> 1 | O77: =SUM(K77:N77) -> 2 | P77: Natural Gas | R77: 62 | S77: =IFERROR(IF(Q77<>"",Q77,R77*0.7457),"Unknown") -> 46.2334 | Y77: =X77*S77 -> 0 | Z77: =IFERROR(INDEX(EFs!B:B,MATCH(P77,EFs!A:A,0))*Dataset!Y77/1000,0) -> 0 | AA77: 33.033925 | AB77: -117.25666 | AC77: 1 | AD77: range_interpolation | AE77: 1010 | AF77: El Camino Real | AI77: Encinitas | AJ77: CA | AK77: San Diego County | AL77: 92024 | AM77: US | AN77: TIGER/LineÂ® dataset from the US Census Bureau
A78: APCD2004-PTO-980295 | B78: Active | C78: 40025 | D78: [34H] California Certified Emergency Standby Engine | E78: Target Store T0274 | F78: T0274 PMT | G78: 1280 Auto Park Way Escondido, CA | H78: 92029 | I78: D | J78: Emergency Engine Generator: _x000D_. Cummins _x000D_. model WSG-1068; _x000D_. serial number I150868217; _x000D_. Engine Family ECEXB06.8GDB; _x000D_max 176 bhp rated (164 firing LPG); fired with natural gas or propane/LPG; equipped with a 3-way catalyst; rich-burn; driving an 85 kW generator | K78: =IFERROR(IF(SEARCH(K$1,$J78)>0,1),0) -> 0 | L78: =IFERROR(IF(SEARCH(L$1,$J78)>0,1),0) -> 0 | M78: =IFERROR(IF(SEARCH(M$1,$J78)>0,1),0) -> 1 | N78: =IFERROR(IF(SEARCH(N$1,$J78)>0,1),0) -> 1 | O78: =SUM(K78:N78) -> 2 | P78: Natural Gas | Q78: 85 | R78: 176 | S78: =IFERROR(IF(Q78<>"",Q78,R78*0.7457),"Unknown") -> 85 | T78: 44561 | U78: 30.30 | V78: 44622 | W78: 45.00 | X78: 14.7 | Y78: =X78*S78 -> 1249.5 | Z78: =IFERROR(INDEX(EFs!B:B,MATCH(P78,EFs!A:A,0))*Dataset!Y78/1000,0) -> 0.90745652 | AA78: 33.11376 | AB78: -117.09977 | AC78: 1 | AD78: rooftop | AE78: 1280 | AF78: Auto Park Way | AI78: Escondido | AJ78: CA | AK78: San Diego County | AL78: 92029 | AM78: US | AN78: San Diego Geographic Information Source - JPA
A79: APCD2004-PTO-980361 | B79: Active | C79: 40025 | D79: [34W] Registered Engine (Rule 12) | E79: Albertsons #2767 | F79: Jill Washburn | G79: 3925 Mission Ave Oceanside, CA | H79: 92058 | I79: A | J79: ONE (1) EMERGENCY ENGINE GENERATOR, 50 HP FORD ENGINE, NATURAL GAS FIRED, MODEL CSG6491-6005-F, S/N 24960 R-04-RK, DRIVING A 30 KW KOHLER GENERATOR MODEL 30RZ82, S/N 380415.APPL# 979831 EFH 12/11/03 | K79: =IFERROR(IF(SEARCH(K$1,$J79)>0,1),0) -> 0 | L79: =IFERROR(IF(SEARCH(L$1,$J79)>0,1),0) -> 0 | M79: =IFERROR(IF(SEARCH(M$1,$J79)>0,1),0) -> 1 | N79: =IFERROR(IF(SEARCH(N$1,$J79)>0,1),0) -> 0 | O79: =SUM(K79:N79) -> 1 | P79: Natural Gas | Q79: 30 | R79: 50 | S79: =IFERROR(IF(Q79<>"",Q79,R79*0.7457),"Unknown") -> 30 | T79: 44510 | U79: 543.70 | V79: 44561 | W79: 543.70 | X79: 0 | Y79: =X79*S79 -> 0 | Z79: =IFERROR(INDEX(EFs!B:B,MATCH(P79,EFs!A:A,0))*Dataset!Y79/1000,0) -> 0 | AA79: 33.227604 | AB79: -117.32393 | AC79: 1 | AD79: rooftop | AE79: 3925 | AF79: Mission Ave | AI79: Oceanside | AJ79: CA | AK79: San Diego County | AL79: 92058 | AM79: US | AN79: San Diego Geographic Information Source - JPA
A80: APCD2004-PTO-980363 | B80: Active | C80: 40025 | D80: [34W] Registered Engine (Rule 12) | E80: Albertsons #3202 | F80: Store Director | G80: 1608 Broadway St El Cajon, CA | H80: 92021 | I80: L | J80: ONE (1) EMERGENCY ENGINE GENERATOR: 50 HP FORD ENGINE, NATURAL GAS FIRED, MODEL CSG6491-6005-F, S/N 35937-1-04-98, DRIVING A KOHLER GENERATOR MODEL 30RZ82, S/N 654880. APPL# 980363 EFH 12/03 | K80: =IFERROR(IF(SEARCH(K$1,$J80)>0,1),0) -> 0 | L80: =IFERROR(IF(SEARCH(L$1,$J80)>0,1),0) -> 0 | M80: =IFERROR(IF(SEARCH(M$1,$J80)>0,1),0) -> 1 | N80: =IFERROR(IF(SEARCH(N$1,$J80)>0,1),0) -> 0 | O80: =SUM(K80:N80) -> 1 | P80: Natural Gas | R80: 50 | S80: =IFERROR(IF(Q80<>"",Q80,R80*0.7457),"Unknown") -> 37.285 | T80: 44538 | U80: 292.30 | V80: 44538 | W80: 300.10 | X80: 7.8 | Y80: =X80*S80 -> 290.823 | Z80: =IFERROR(INDEX(EFs!B:B,MATCH(P80,EFs!A:A,0))*Dataset!Y80/1000,0) -> 0.21121187 | AA80: 32.808988 | AB80: -116.92013 | AC80: 1 | AD80: rooftop | AE80: 1608 | AF80: Broadway | AI80: El Cajon | AJ80: CA | AK80: San Diego County | AL80: 92021 | AM80: US | AN80: San Diego Geographic Information Source - JPA
A81: APCD2004-PTO-980365 | B81: Active | C81: 40025 | D81: [34W] Registered Engine (Rule 12) | E81: Albertsons #2785 | F81: Jill Washburn | G81: 8650 Lake Murray Blvd San Diego, CA | H81: 92119 | I81: J | J81: ONE (1) EMERGENCY ENGINE GENERATOR, 50 HP FORD ENGINE, NATURAL GAS FIRED MODEL CSG6491-6005-F, S/N 31983E-20-RK, DRIVING A KOHLER GENERATOR MODEL 30RZ82, S/N 384720. APP# 980365 EFH 12/03 | K81: =IFERROR(IF(SEARCH(K$1,$J81)>0,1),0) -> 0 | L81: =IFERROR(IF(SEARCH(L$1,$J81)>0,1),0) -> 0 | M81: =IFERROR(IF(SEARCH(M$1,$J81)>0,1),0) -> 1 | N81: =IFERROR(IF(SEARCH(N$1,$J81)>0,1),0) -> 0 | O81: =SUM(K81:N81) -> 1 | P81: Natural Gas | R81: 50 | S81: =IFERROR(IF(Q81<>"",Q81,R81*0.7457),"Unknown") -> 37.285 | T81: 44562 | U81: 323.80 | V81: 44562 | W81: 331.50 | X81: 7.7 | Y81: =X81*S81 -> 287.0945 | Z81: =IFERROR(INDEX(EFs!B:B,MATCH(P81,EFs!A:A,0))*Dataset!Y81/1000,0) -> 0.20850402 | AA81: 32.802686 | AB81: -117.01284 | AC81: 1 | AD81: rooftop | AE81: 8650 | AF81: Lake Murray Blvd | AI81: San Diego | AJ81: CA | AK81: San Diego County | AL81: 92119 | AM81: US | AN81: San Diego Geographic Information Source - JPA
A82: APCD2004-PTO-980366 | B82: Active | C82: 40025 | D82: [34W] Registered Engine (Rule 12) | E82: Albertsons #1705 | F82: Jill Washburn | G82: 1570 W Valley Pkwy Escondido, CA | H82: 92029 | I82: D | J82: ONE (1) EMERGENCY ENGINE GENERATOR, 50 HP FORD ENGINE, NATURAL GAS FIRED, MODEL CSG6491-6005-F, S/N 11404 K-19-RC, DRIVING A KOHLER GENERATOR MODEL 30RZ82, S/N 366930. | K82: =IFERROR(IF(SEARCH(K$1,$J82)>0,1),0) -> 0 | L82: =IFERROR(IF(SEARCH(L$1,$J82)>0,1),0) -> 0 | M82: =IFERROR(IF(SEARCH(M$1,$J82)>0,1),0) -> 1 | N82: =IFERROR(IF(SEARCH(N$1,$J82)>0,1),0) -> 0 | O82: =SUM(K82:N82) -> 1 | P82: Natural Gas | R82: 50 | S82: =IFERROR(IF(Q82<>"",Q82,R82*0.7457),"Unknown") -> 37.285 | T82: 44561 | U82: 842.10 | V82: 44734 | W82: 892.50 | X82: 50.4 | Y82: =X82*S82 -> 1879.164 | Z82: =IFERROR(INDEX(EFs!B:B,MATCH(P82,EFs!A:A,0))*Dataset!Y82/1000,0) -> 1.3647536 | AA82: 33.109876 | AB82: -117.10405 | AC82: 1 | AD82: range_interpolation | AE82: 1570 | AF82: W Valley Pkwy | AI82: Escondido | AJ82: CA | AK82: San Diego County | AL82: 92029 | AM82: US | AN82: TIGER/LineÂ® dataset from the US Census Bureau
A83: APCD2004-PTO-980862 | B83: Active | C83: 40025 | D83: [34W] Registered Engine (Rule 12) | E83: Target Store T1140 | F83: General Manager | G83: 2911 Jamacha Rd El Cajon, CA | H83: 92019 | I83: L | J83: EMERGENCY STANDBY ENGINE: FORD ENGINE, FUELED WITH NATURAL GAS, MODEL CSG-6491-6005-A, S/N 17407 H-23-RH, RATED AT 82 BHP, MANUFACTURE YEAR: OCTOBER 1998. DRIVING A 35KW GENERATOR. (980862-CCN-10/04) | K83: =IFERROR(IF(SEARCH(K$1,$J83)>0,1),0) -> 0 | L83: =IFERROR(IF(SEARCH(L$1,$J83)>0,1),0) -> 0 | M83: =IFERROR(IF(SEARCH(M$1,$J83)>0,1),0) -> 1 | N83: =IFERROR(IF(SEARCH(N$1,$J83)>0,1),0) -> 0 | O83: =SUM(K83:N83) -> 1 | P83: Natural Gas | Q83: 35 | R83: 82 | S83: =IFERROR(IF(Q83<>"",Q83,R83*0.7457),"Unknown") -> 35 | T83: 44566 | U83: 244.00 | V83: 44566 | W83: 244.00 | X83: 0 | Y83: =X83*S83 -> 0 | Z83: =IFERROR(INDEX(EFs!B:B,MATCH(P83,EFs!A:A,0))*Dataset!Y83/1000,0) -> 0 | AA83: 32.738689 | AB83: -116.93896 | AC83: 1 | AD83: rooftop | AE83: 2911 | AF83: Jamacha Rd | AI83: El Cajon | AJ83: CA | AK83: San Diego County | AL83: 92019 | AM83: US | AN83: San Diego Geographic Information Source - JPA
A84: APCD2004-PTO-982134 | B84: Active | C84: 40025 | D84: [34C] Emergency Standby Engine | E84: Motivational Systems Inc | F84: Pete Relph | G84: 2200 Cleveland Av National City, CA | H84: 91950 | I84: Q | J84: INTERNAL COMBUSTION ENGINE. GENERATION PACKAGE: GENERAC. ENGINE MODEL: 5.7GN. BHP RATING: 91 HP. NATURAL GAS FUELED. NATURALLY ASPIRATED. EQUIPPED WITH A CATALYTIC CONVERTER AND AIR TO FUEL RATIO CONTROLLER. DRIVES AN ELECTRICAL EMERGENCY GENERATOR RATED AT 57 KW. JFTNEWDEC2204 | K84: =IFERROR(IF(SEARCH(K$1,$J84)>0,1),0) -> 0 | L84: =IFERROR(IF(SEARCH(L$1,$J84)>0,1),0) -> 0 | M84: =IFERROR(IF(SEARCH(M$1,$J84)>0,1),0) -> 1 | N84: =IFERROR(IF(SEARCH(N$1,$J84)>0,1),0) -> 0 | O84: =SUM(K84:N84) -> 1 | P84: Natural Gas | Q84: 57 | R84: 91 | S84: =IFERROR(IF(Q84<>"",Q84,R84*0.7457),"Unknown") -> 57 | T84: 44602 | U84: 101.40 | V84: 44602 | W84: 101.40 | X84: 0 | Y84: =X84*S84 -> 0 | Z84: =IFERROR(INDEX(EFs!B:B,MATCH(P84,EFs!A:A,0))*Dataset!Y84/1000,0) -> 0 | AA84: 32.661221 | AB84: -117.11068 | AC84: 1 | AD84: rooftop | AE84: 2200 | AF84: Cleveland Ave | AI84: National City | AJ84: CA | AK84: San Diego County | AL84: 91950 | AM84: US | AN84: San Diego Geographic Information Source - JPA
A85: APCD2005-PTO-040953 | B85: Active | C85: 40025 | D85: [34C] Emergency Standby Engine | E85: SD City of Police Dept | F85: Owner Manager | G85: 1401 Broadway San Diego, CA | H85: 92101 | I85: N | J85: EMERGENCY DIESEL ENGINE GENERATOR SET, CATERPILLAR MODEL 3508STD, S/N 23Z1034 1096 BHP, 750 KW, USING NO. 2 DIESEL FUEL. | K85: =IFERROR(IF(SEARCH(K$1,$J85)>0,1),0) -> 1 | L85: =IFERROR(IF(SEARCH(L$1,$J85)>0,1),0) -> 0 | M85: =IFERROR(IF(SEARCH(M$1,$J85)>0,1),0) -> 0 | N85: =IFERROR(IF(SEARCH(N$1,$J85)>0,1),0) -> 0 | O85: =SUM(K85:N85) -> 1 | P85: Diesel | Q85: 750 | R85: 1096 | S85: =IFERROR(IF(Q85<>"",Q85,R85*0.7457),"Unknown") -> 750 | T85: 44449 | U85: 264.60 | V85: 44747 | W85: 274.50 | X85: 9.9 | Y85: =X85*S85 -> 7425 | Z85: =IFERROR(INDEX(EFs!B:B,MATCH(P85,EFs!A:A,0))*Dataset!Y85/1000,0) -> 6.7448174 | AA85: 32.715257 | AB85: -117.15093 | AC85: 1 | AD85: rooftop | AE85: 1401 | AF85: Broadway | AI85: San Diego | AJ85: CA | AK85: San Diego County | AL85: 92101 | AM85: US | AN85: San Diego Geographic Information Source - JPA
A86: APCD2005-PTO-860109 | B86: Active | C86: 40025 | D86: [34C] Emergency Standby Engine | E86: Richard J Donovan Correctional Facility | F86: Daniel McCourt | G86: 480 Alta Rd San Diego, CA | H86: 92179 | I86: R | J86: EMERGENCY DIESEL ENGINE GENERATOR SET, CATERPILLAR MODEL 3512 DITA, 1000 KW, 1471 HP, USING NO. 2 DIESEL FUEL. APPL. 860109/GEA 1087 APPL#86010917CCR93115SJE12/05 | K86: =IFERROR(IF(SEARCH(K$1,$J86)>0,1),0) -> 1 | L86: =IFERROR(IF(SEARCH(L$1,$J86)>0,1),0) -> 0 | M86: =IFERROR(IF(SEARCH(M$1,$J86)>0,1),0) -> 0 | N86: =IFERROR(IF(SEARCH(N$1,$J86)>0,1),0) -> 0 | O86: =SUM(K86:N86) -> 1 | P86: Diesel | Q86: 1000 | R86: 1471 | S86: =IFERROR(IF(Q86<>"",Q86,R86*0.7457),"Unknown") -> 1000 | T86: 44448 | U86: 688.10 | V86: 44448 | W86: 695.30 | X86: 7.2 | Y86: =X86*S86 -> 7200 | Z86: =IFERROR(INDEX(EFs!B:B,MATCH(P86,EFs!A:A,0))*Dataset!Y86/1000,0) -> 6.540429 | AA86: 32.581148 | AB86: -116.92725 | AC86: 1 | AD86: rooftop | AE86: 480 | AF86: Alta Rd | AI86: San Diego | AJ86: CA | AK86: San Diego County | AL86: 92179 | AM86: US | AN86: San Diego Geographic Information Source - JPA
A87: APCD2005-PTO-870525 | B87: Active | C87: 40025 | D87: [34C] Emergency Standby Engine | E87: SD Marriott Hotel & Marina | F87: Facility Manager | G87: 333 Harbor Dr W San Diego, CA | H87: 92101 | I87: N | J87: EMERGENCY GENERATOR: CATERPILLAR MODEL 3412, 755 HP RATED 600 KW, #2 DIESEL FIRED, S/N 81Z05291 (APPL #870525/JJS) 0688 870525 17CCR93115 SJE12/05 | K87: =IFERROR(IF(SEARCH(K$1,$J87)>0,1),0) -> 1 | L87: =IFERROR(IF(SEARCH(L$1,$J87)>0,1),0) -> 0 | M87: =IFERROR(IF(SEARCH(M$1,$J87)>0,1),0) -> 0 | N87: =IFERROR(IF(SEARCH(N$1,$J87)>0,1),0) -> 0 | O87: =SUM(K87:N87) -> 1 | P87: Diesel | Q87: 600 | R87: 755 | S87: =IFERROR(IF(Q87<>"",Q87,R87*0.7457),"Unknown") -> 600 | Y87: =X87*S87 -> 0 | Z87: =IFERROR(INDEX(EFs!B:B,MATCH(P87,EFs!A:A,0))*Dataset!Y87/1000,0) -> 0 | AA87: 32.706246 | AB87: -117.15947 | AC87: 1 | AD87: range_interpolation | AE87: 333 | AF87: Harbor Dr | AI87: San Diego | AJ87: CA | AK87: San Diego County | AL87: 92101 | AM87: US | AN87: TIGER/LineÂ® dataset from the US Census Bureau
A88: APCD2005-PTO-890253 | B88: Active | C88: 40025 | D88: [34C] Emergency Standby Engine | E88: Doubletree by Hilton San Diego Mission Valley | F88: Marjorie Maehler | G88: 10950 Torrey Pines Rd N San Diego, CA | H88: 92037 | I88: I | J88: EMERGENCY GENERATOR: CUMMINS MODEL KTA-19/2, WITH TURBOCHARGE AND AFTERCOOLING, RATED 600 HP AT 400 KW, DIESEL OIL FIRED, S/N 37125235. 972822 (2/99) 17 CCR 93115 SJE 12/05 | K88: =IFERROR(IF(SEARCH(K$1,$J88)>0,1),0) -> 1 | L88: =IFERROR(IF(SEARCH(L$1,$J88)>0,1),0) -> 0 | M88: =IFERROR(IF(SEARCH(M$1,$J88)>0,1),0) -> 0 | N88: =IFERROR(IF(SEARCH(N$1,$J88)>0,1),0) -> 0 | O88: =SUM(K88:N88) -> 1 | P88: Diesel | Q88: 400 | R88: 600 | S88: =IFERROR(IF(Q88<>"",Q88,R88*0.7457),"Unknown") -> 400 | T88: 44685 | U88: 71.00 | V88: 44685 | W88: 71.00 | X88: 0 | Y88: =X88*S88 -> 0 | Z88: =IFERROR(INDEX(EFs!B:B,MATCH(P88,EFs!A:A,0))*Dataset!Y88/1000,0) -> 0 | AA88: 32.902471 | AB88: -117.24283 | AC88: 0.9 | AD88: nearest_rooftop_match | AE88: 10950 | AF88: N Torrey Pines Rd | AI88: LA Jolla | AJ88: CA | AK88: San Diego County | AL88: 92037 | AM88: US | AN88: San Diego Geographic Information Source - JPA
A89: APCD2005-PTO-890311 | B89: Active | C89: 40025 | D89: [34C] Emergency Standby Engine | E89: 450 B Street Investors LLC | F89: Tanya Vafaee | G89: 450 B Street San Diego, CA | H89: 92101 | I89: N | J89: EMERGENCY GENERATOR: DETROIT DIESEL MODEL 8123-7300, RATED 780 HP, WITH TURBOCHARGE, DIESEL OIL FIRED, S/N 12VF000648. 973099 (3/99) 17 CCR 93115 SJE 11/05 | K89: =IFERROR(IF(SEARCH(K$1,$J89)>0,1),0) -> 1 | L89: =IFERROR(IF(SEARCH(L$1,$J89)>0,1),0) -> 0 | M89: =IFERROR(IF(SEARCH(M$1,$J89)>0,1),0) -> 0 | N89: =IFERROR(IF(SEARCH(N$1,$J89)>0,1),0) -> 0 | O89: =SUM(K89:N89) -> 1 | P89: Diesel | R89: 780 | S89: =IFERROR(IF(Q89<>"",Q89,R89*0.7457),"Unknown") -> 581.646 | Y89: =X89*S89 -> 0 | Z89: =IFERROR(INDEX(EFs!B:B,MATCH(P89,EFs!A:A,0))*Dataset!Y89/1000,0) -> 0 | AA89: 32.718525 | AB89: -117.16067 | AC89: 1 | AD89: rooftop | AE89: 450 | AF89: B St | AI89: San Diego | AJ89: CA | AK89: San Diego County | AL89: 92101 | AM89: US | AN89: San Diego Geographic Information Source - JPA
A90: APCD2005-PTO-890337 | B90: Active | C90: 40025 | D90: [34C] Emergency Standby Engine | E90: MCI | F90: Owner Manager | G90: 8933 Complex Dr San Diego, CA | H90: 92123 | I90: J | J90: Caterpillar Model; SR4-3412, S/N: 81Z03032 - Diesel Fired, 680 hp I.C. Engine Driving 470 KW Electrical Generator. Emergency Stand-by Electrical Generator. AA - 11/07/89 890337 17CCR93115 SJE11/05 (ATCM DATA: S/N 81Z03032) | K90: =IFERROR(IF(SEARCH(K$1,$J90)>0,1),0) -> 1 | L90: =IFERROR(IF(SEARCH(L$1,$J90)>0,1),0) -> 0 | M90: =IFERROR(IF(SEARCH(M$1,$J90)>0,1),0) -> 0 | N90: =IFERROR(IF(SEARCH(N$1,$J90)>0,1),0) -> 0 | O90: =SUM(K90:N90) -> 1 | P90: Diesel | Q90: 470 | R90: 680 | S90: =IFERROR(IF(Q90<>"",Q90,R90*0.7457),"Unknown") -> 470 | T90: 44562 | U90: 658.00 | V90: 44562 | W90: 663.00 | X90: 5 | Y90: =X90*S90 -> 2350 | Z90: =IFERROR(INDEX(EFs!B:B,MATCH(P90,EFs!A:A,0))*Dataset!Y90/1000,0) -> 2.1347234 | AA90: 32.829982 | AB90: -117.13429 | AC90: 1 | AD90: rooftop | AE90: 8933 | AF90: Complex Dr | AI90: San Diego | AJ90: CA | AK90: San Diego County | AL90: 92123 | AM90: US | AN90: San Diego Geographic Information Source - JPA
A91: APCD2005-PTO-890450 | B91: Active | C91: 40025 | D91: [34C] Emergency Standby Engine | E91: SD Convention Center Corp | F91: Assistant Eng Mgr | G91: 111 Harbor Dr W San Diego, CA | H91: 92101 | I91: N | J91: EMERGENCY STANDBY ELECTRICAL GENERATOR CONSISTING OF CUMMINS KTA50 1490 BHP DIESEL FIRED I.C. ENGINE DRIVING A 1025 KW ELECTRICAL GENERATOR AA - DECEMBER 27, 1989 89045089045117CCR93115SJE11/05 (ATCM DATA: S/N 33113511) | K91: =IFERROR(IF(SEARCH(K$1,$J91)>0,1),0) -> 1 | L91: =IFERROR(IF(SEARCH(L$1,$J91)>0,1),0) -> 0 | M91: =IFERROR(IF(SEARCH(M$1,$J91)>0,1),0) -> 0 | N91: =IFERROR(IF(SEARCH(N$1,$J91)>0,1),0) -> 0 | O91: =SUM(K91:N91) -> 1 | P91: Diesel | Q91: 25 | R91: 1490 | S91: =IFERROR(IF(Q91<>"",Q91,R91*0.7457),"Unknown") -> 25 | Y91: =X91*S91 -> 0 | Z91: =IFERROR(INDEX(EFs!B:B,MATCH(P91,EFs!A:A,0))*Dataset!Y91/1000,0) -> 0 | AA91: 32.709336 | AB91: -117.16506 | AC91: 0.9 | AD91: range_interpolation | AE91: 111 | AF91: W Harbor Dr | AI91: San Diego | AJ91: CA | AK91: San Diego County | AL91: 92101 | AM91: US | AN91: TIGER/LineÂ® dataset from the US Census Bureau
A92: APCD2005-PTO-890451 | B92: Active | C92: 40025 | D92: [34C] Emergency Standby Engine | E92: SD Convention Center Corp | F92: Assist Eng Mgr | G92: 111 Harbor Dr W San Diego, CA | H92: 92101 | I92: N | J92: EMERGENCY WATER PUMP CONSISTING OF ONE CATERPILLAR MODEL 8AF20-BF DIESEL FIRED 235 BHP I.C. ENGINE, S/N 03Z06816, DRIVING ONE PEERLESS MODEL 8AF20-B WATER PUMP A. ABREU, FEBRUARY 22,1990 890451 890450 17CCR93115 SJE12/05 | K92: =IFERROR(IF(SEARCH(K$1,$J92)>0,1),0) -> 1 | L92: =IFERROR(IF(SEARCH(L$1,$J92)>0,1),0) -> 0 | M92: =IFERROR(IF(SEARCH(M$1,$J92)>0,1),0) -> 0 | N92: =IFERROR(IF(SEARCH(N$1,$J92)>0,1),0) -> 0 | O92: =SUM(K92:N92) -> 1 | P92: Diesel | R92: 235 | S92: =IFERROR(IF(Q92<>"",Q92,R92*0.7457),"Unknown") -> 175.2395 | Y92: =X92*S92 -> 0 | Z92: =IFERROR(INDEX(EFs!B:B,MATCH(P92,EFs!A:A,0))*Dataset!Y92/1000,0) -> 0 | AA92: 32.709336 | AB92: -117.16506 | AC92: 0.9 | AD92: range_interpolation | AE92: 111 | AF92: W Harbor Dr | AI92: San Diego | AJ92: CA | AK92: San Diego County | AL92: 92101 | AM92: US | AN92: TIGER/LineÂ® dataset from the US Census Bureau
A93: APCD2005-PTO-890483 | B93: Active | C93: 40025 | D93: [34C] Emergency Standby Engine | E93: Oceanside City Of Water Utilities Dep SLRWWTP | F93: Managing Director | G93: 3950 River Rd N Oceanside, CA | H93: 92058 | I93: A | J93: DIESEL ENGINE/EMERGENCY GENERATOR SET: ONE (1) CATERPILLAR MODEL 3512 DITA, V-12, DIRECT INJECTION, TURBOCHARGED, AFTERCOOLED, 2168 BHP MAXIMUM RATED POWER OUTPUT; DRIVING A 1500 KW, 1800 RPM ELECTRICAL GENERATOR. 17CCR93115 SJE11/05 (ATCM DATA: S/N 3YF00432) | K93: =IFERROR(IF(SEARCH(K$1,$J93)>0,1),0) -> 1 | L93: =IFERROR(IF(SEARCH(L$1,$J93)>0,1),0) -> 0 | M93: =IFERROR(IF(SEARCH(M$1,$J93)>0,1),0) -> 0 | N93: =IFERROR(IF(SEARCH(N$1,$J93)>0,1),0) -> 0 | O93: =SUM(K93:N93) -> 1 | P93: Diesel | Q93: 500 | R93: 2168 | S93: =IFERROR(IF(Q93<>"",Q93,R93*0.7457),"Unknown") -> 500 | T93: 44327 | U93: 174.00 | V93: 44327 | W93: 236.00 | X93: 62 | Y93: =X93*S93 -> 31000 | Z93: =IFERROR(INDEX(EFs!B:B,MATCH(P93,EFs!A:A,0))*Dataset!Y93/1000,0) -> 28.160181 | AA93: 33.248545 | AB93: -117.33149 | AC93: 0.9 | AD93: rooftop | AE93: 3950 | AF93: N River Rd | AI93: Oceanside | AJ93: CA | AK93: San Diego County | AL93: 92058 | AM93: US | AN93: San Diego Geographic Information Source - JPA
A94: APCD2005-PTO-890800 | B94: Active | C94: 40025 | D94: [34C] Emergency Standby Engine | E94: General Atomics | F94: Vera Mitrofski | G94: 16530 Via Esprillo San Diego, CA | H94: 92127 | I94: F | J94: EMERGENCY GENERATOR SET: DIESEL ENGINE (890 HP), CATERPILLAR, MODEL 3412 TA, S/N 81Z09030 (LOCATION BLDG 2 NORTH) (APPL #890900/CW) 0591 890900 17 CCR 93115 SJE 10/05 | K94: =IFERROR(IF(SEARCH(K$1,$J94)>0,1),0) -> 1 | L94: =IFERROR(IF(SEARCH(L$1,$J94)>0,1),0) -> 0 | M94: =IFERROR(IF(SEARCH(M$1,$J94)>0,1),0) -> 0 | N94: =IFERROR(IF(SEARCH(N$1,$J94)>0,1),0) -> 0 | O94: =SUM(K94:N94) -> 1 | P94: Diesel | R94: 890 | S94: =IFERROR(IF(Q94<>"",Q94,R94*0.7457),"Unknown") -> 663.673 | T94: 44538 | U94: 213.00 | V94: 44538 | W94: 221.00 | X94: 8 | Y94: =X94*S94 -> 5309.384 | Z94: =IFERROR(INDEX(EFs!B:B,MATCH(P94,EFs!A:A,0))*Dataset!Y94/1000,0) -> 4.8230068 | AA94: 33.016398 | AB94: -117.09212 | AC94: 1 | AD94: rooftop | AE94: 16530 | AF94: Via Esprillo | AI94: San Diego | AJ94: CA | AK94: San Diego County | AL94: 92127 | AM94: US | AN94: San Diego Geographic Information Source - JPA
A95: APCD2005-PTO-890850 | B95: Active | C95: 40025 | D95: [34C] Emergency Standby Engine | E95: Ramona Municipal Water District | F95: Tom McKernan | G95: 22758 San Vicente Rd Ramona, CA | H95: 92065 | I95: F | J95: EMERGENCY ENGINE GENERATOR SET: ONAN-CUMMINS DIESEL ENGINE GENERATOR MODEL NO. KTA19-G2, S/N 60600324, 600 BHP (448 KW) AT 1800 RPM, TURBOCHARGED. 89085017CCR93115SJE12/05 | K95: =IFERROR(IF(SEARCH(K$1,$J95)>0,1),0) -> 1 | L95: =IFERROR(IF(SEARCH(L$1,$J95)>0,1),0) -> 0 | M95: =IFERROR(IF(SEARCH(M$1,$J95)>0,1),0) -> 0 | N95: =IFERROR(IF(SEARCH(N$1,$J95)>0,1),0) -> 0 | O95: =SUM(K95:N95) -> 1 | P95: Diesel | Q95: 448 | R95: 600 | S95: =IFERROR(IF(Q95<>"",Q95,R95*0.7457),"Unknown") -> 448 | T95: 44532 | U95: 229.20 | V95: 44532 | W95: 252.70 | X95: 23.5 | Y95: =X95*S95 -> 10528 | Z95: =IFERROR(INDEX(EFs!B:B,MATCH(P95,EFs!A:A,0))*Dataset!Y95/1000,0) -> 9.5635607 | AA95: 33.000122 | AB95: -116.83764 | AC95: 1 | AD95: rooftop | AE95: 22758 | AF95: San Vicente Rd | AI95: Ramona | AJ95: CA | AK95: San Diego County | AL95: 92065 | AM95: US | AN95: San Diego Geographic Information Source - JPA
A96: APCD2005-PTO-890860 | B96: Active | C96: 40025 | D96: [34C] Emergency Standby Engine | E96: SD CO OF MENTAL HEALTH PR0385 | G96: 3851 ROSECRANS ST SAN DIEGO, CA | H96: 92110 | I96: I | J96: CUMMINS ENGINE GENERATOR, MODEL 85564, 375 BHP, 180KW, SN 11511104, 1800 RPM DIESEL FIRED. 890860 EFH 08/23/91 17 CCR 93115 SJE 11/05 | K96: =IFERROR(IF(SEARCH(K$1,$J96)>0,1),0) -> 1 | L96: =IFERROR(IF(SEARCH(L$1,$J96)>0,1),0) -> 0 | M96: =IFERROR(IF(SEARCH(M$1,$J96)>0,1),0) -> 0 | N96: =IFERROR(IF(SEARCH(N$1,$J96)>0,1),0) -> 0 | O96: =SUM(K96:N96) -> 1 | P96: Diesel | Q96: 180 | R96: 375 | S96: =IFERROR(IF(Q96<>"",Q96,R96*0.7457),"Unknown") -> 180 | Y96: =X96*S96 -> 0 | Z96: =IFERROR(INDEX(EFs!B:B,MATCH(P96,EFs!A:A,0))*Dataset!Y96/1000,0) -> 0 | AA96: 32.752832 | AB96: -117.20179 | AC96: 1 | AD96: rooftop | AE96: 3851 | AF96: Rosecrans St | AI96: San Diego | AJ96: CA | AK96: San Diego County | AL96: 92110 | AM96: US | AN96: San Diego Geographic Information Source - JPA
A97: APCD2005-PTO-890863 | B97: Active | C97: 40025 | D97: [34C] Emergency Standby Engine | E97: East County Regional Center, JCC #37-I1 | F97: Donna Jorgensen | G97: 250 E Main St El Cajon, CA | H97: 92020 | I97: L | J97: IC ENGINE, DETROIT DIESEL, MODEL: 10647110, UNIT: 6A0399362, S/N: 5148549163 BHP AT 1750 RPM. 890863 17CCR93115 SJE 12/05 | K97: =IFERROR(IF(SEARCH(K$1,$J97)>0,1),0) -> 1 | L97: =IFERROR(IF(SEARCH(L$1,$J97)>0,1),0) -> 0 | M97: =IFERROR(IF(SEARCH(M$1,$J97)>0,1),0) -> 0 | N97: =IFERROR(IF(SEARCH(N$1,$J97)>0,1),0) -> 0 | O97: =SUM(K97:N97) -> 1 | P97: Diesel | R97: Unknown | S97: =IFERROR(IF(Q97<>"",Q97,R97*0.7457),"Unknown") -> Unknown | T97: 44481 | U97: 826.85 | V97: 44481 | W97: 845.89 | X97: 19.04 | Y97: =X97*S97 -> #VALUE! | Z97: =IFERROR(INDEX(EFs!B:B,MATCH(P97,EFs!A:A,0))*Dataset!Y97/1000,0) -> 0 | AA97: 32.796916 | AB97: -116.95888 | AC97: 1 | AD97: rooftop | AE97: 250 | AF97: E Main St E | AI97: El Cajon | AJ97: CA | AK97: San Diego County | AL97: 92020 | AM97: US | AN97: San Diego Geographic Information Source - JPA
A98: APCD2005-PTO-891156 | B98: Active | C98: 40025 | D98: [34C] Emergency Standby Engine | E98: SD Family Housing LLC | F98: Owner Manager | G98: 1405 Leyte Rd Coronado, CA | H98: 92118 | I98: O | J98: CATERPILLAR MODEL 3114, 119 HP, TURBO CHARGED, AFTER COOLED DIESEL ENGINE, S/N 6AF00547, POWERING 2 GORMAN-RUPP SEWAGE LIFT PUMPS ONLY. (APP# 891156/GDS) 11/91 SILVER STRAND HOUSING (978130 5/02) NO APP 17CCR93115 SJE11/05 | K98: =IFERROR(IF(SEARCH(K$1,$J98)>0,1),0) -> 1 | L98: =IFERROR(IF(SEARCH(L$1,$J98)>0,1),0) -> 0 | M98: =IFERROR(IF(SEARCH(M$1,$J98)>0,1),0) -> 0 | N98: =IFERROR(IF(SEARCH(N$1,$J98)>0,1),0) -> 0 | O98: =SUM(K98:N98) -> 1 | P98: Diesel | R98: 119 | S98: =IFERROR(IF(Q98<>"",Q98,R98*0.7457),"Unknown") -> 88.7383 | T98: 44363 | U98: 455.00 | V98: 44778 | W98: 511.00 | X98: 56 | Y98: =X98*S98 -> 4969.3448 | Z98: =IFERROR(INDEX(EFs!B:B,MATCH(P98,EFs!A:A,0))*Dataset!Y98/1000,0) -> 4.5141176 | AA98: 32.64701 | AB98: -117.14548 | AC98: 1 | AD98: range_interpolation | AE98: 1405 | AF98: Leyte Rd | AI98: Coronado | AJ98: CA | AK98: San Diego County | AL98: 92118 | AM98: US | AN98: TIGER/LineÂ® dataset from the US Census Bureau
A99: APCD2005-PTO-900083 | B99: Active | C99: 40025 | D99: [34C] Emergency Standby Engine | E99: Oceanside City Of Water Utilities | F99: Lori Rigby | G99: 1520 Sleeping Indian Rd Oceanside, CA | H99: 92058 | I99: A | J99: DIESEL EMERGENCY GENERATOR: CATERPILLAR MODEL 3306 BDI, 335 BHP MAXIMUM RATED POWER OUTPUT, SN 2AJ00464; EQUIPPED WITH TURBOCHARGING AND AFTERCOOLING; DRIVING A 225 KW GENERATOR. (APPL#900083/KMC/0291) 900083 17CCR93115 SJE11/05 | K99: =IFERROR(IF(SEARCH(K$1,$J99)>0,1),0) -> 1 | L99: =IFERROR(IF(SEARCH(L$1,$J99)>0,1),0) -> 0 | M99: =IFERROR(IF(SEARCH(M$1,$J99)>0,1),0) -> 0 | N99: =IFERROR(IF(SEARCH(N$1,$J99)>0,1),0) -> 0 | O99: =SUM(K99:N99) -> 1 | P99: Diesel | Q99: 225 | R99: 335 | S99: =IFERROR(IF(Q99<>"",Q99,R99*0.7457),"Unknown") -> 225 | T99: 44328 | U99: 585.40 | V99: 44328 | W99: 588.50 | X99: 3.1 | Y99: =X99*S99 -> 697.5 | Z99: =IFERROR(INDEX(EFs!B:B,MATCH(P99,EFs!A:A,0))*Dataset!Y99/1000,0) -> 0.63360406 | AA99: 33.320912 | AB99: -117.26248 | AC99: 0.9 | AD99: range_interpolation | AE99: 1520 | AF99: Sleeping Indian Rd | AI99: Fallbrook | AJ99: CA | AK99: San Diego County | AL99: 92028 | AM99: US | AN99: TIGER/LineÂ® dataset from the US Census Bureau
A100: APCD2005-PTO-900301 | B100: Active | C100: 40025 | D100: [34H] California Certified Emergency Standby Engine | E100: USN Nav Sta 1 SCE | F100: Commanding Officer | G100: Naval Station San Diego, CA | H100: 92136 | I100: S | J100: Emergency Diesel Engine Generator: FPT Industrial, Model F3AE9685A*E, 449 bhp, S/N E003-210695, Model Year 2021, Tier 3 certified of Engine Family Number MFPXL10.3TR3; driving a 300-kW emergency electrical generator. Vertical exhaust with raincap, 17 feet above ground. | K100: =IFERROR(IF(SEARCH(K$1,$J100)>0,1),0) -> 1 | L100: =IFERROR(IF(SEARCH(L$1,$J100)>0,1),0) -> 0 | M100: =IFERROR(IF(SEARCH(M$1,$J100)>0,1),0) -> 0 | N100: =IFERROR(IF(SEARCH(N$1,$J100)>0,1),0) -> 0 | O100: =SUM(K100:N100) -> 1 | P100: Diesel | Q100: 300 | R100: 449 | S100: =IFERROR(IF(Q100<>"",Q100,R100*0.7457),"Unknown") -> 300 | T100: 44685 | U100: 1.20 | V100: 44685 | W100: 3.30 | X100: 2.1 | Y100: =X100*S100 -> 630 | Z100: =IFERROR(INDEX(EFs!B:B,MATCH(P100,EFs!A:A,0))*Dataset!Y100/1000,0) -> 0.57228754 | AA100: 32.812175 | AB100: -116.93277 | AC100: 0.86 | AD100: street_center | AF100: Navello St | AI100: El Cajon | AJ100: CA | AK100: San Diego County | AL100: 92021 | AM100: US | AN100: TIGER/LineÂ® dataset from the US Census Bureau
...

Sheet EFs
A1: Fuel | B1: CO2 Mt/MWh
A2: Diesel | B2: 0.90839292
A3: Natural Gas | B3: 0.72625572
A4: Gasoline | B4: 0.79502531
A5: Oil | B5: 0.93205218
A6: LPG | B6: 0.99271569
A7: Propane | B7: 0.8239

Sheet Summary
A1: Fuel | B1: Count of Gensets | C1: Average Capacity (kW) | D1: Total Capacity (MW) | E1: Estimated Generation (MWh) | F1: Average Operational Hours | G1: Total Operational Hours
A2: Diesel | B2: =COUNTIFS(Dataset!P:P,A2,Dataset!B:B,"Active") -> 2874 | C2: =AVERAGEIFS(Dataset!S:S,Dataset!P:P,A2,Dataset!S:S,">0",Dataset!S:S,"<>Unknown",Dataset!B:B,"Active") -> 355.71183 | D2: =SUMIFS(Dataset!S:S,Dataset!P:P,A2,Dataset!S:S,">0",Dataset!B:B,"Active")/1000 -> 1018.0473 | E2: =SUMIFS(Dataset!Y:Y,Dataset!P:P,A2,Dataset!Y:Y,">0",Dataset!B:B,"Active")/1000 -> 9405.6979 | F2: =AVERAGEIFS(Dataset!X:X,Dataset!P:P,A2,Dataset!X:X,">0",Dataset!B:B,"Active") -> 12.407365 | G2: =SUMIFS(Dataset!X:X,Dataset!P:P,A2,Dataset!X:X,">0",Dataset!B:B,"Active") -> 25335.84
A3: Propane | B3: =COUNTIFS(Dataset!P:P,A3,Dataset!B:B,"Active") -> 130 | C3: =AVERAGEIFS(Dataset!S:S,Dataset!P:P,A3,Dataset!S:S,">0",Dataset!S:S,"<>Unknown",Dataset!B:B,"Active") -> 77.07996 | D3: =SUMIFS(Dataset!S:S,Dataset!P:P,A3,Dataset!S:S,">0",Dataset!B:B,"Active")/1000 -> 9.8662348 | E3: =SUMIFS(Dataset!Y:Y,Dataset!P:P,A3,Dataset!Y:Y,">0",Dataset!B:B,"Active")/1000 -> 152.88678 | F3: =AVERAGEIFS(Dataset!X:X,Dataset!P:P,A3,Dataset!X:X,">0",Dataset!B:B,"Active") -> 24.353977 | G3: =SUMIFS(Dataset!X:X,Dataset!P:P,A3,Dataset!X:X,">0",Dataset!B:B,"Active") -> 2143.15
A4: Natural Gas | B4: =COUNTIFS(Dataset!P:P,A4,Dataset!B:B,"Active") -> 228 | C4: =AVERAGEIFS(Dataset!S:S,Dataset!P:P,A4,Dataset!S:S,">0",Dataset!S:S,"<>Unknown",Dataset!B:B,"Active") -> 120.58276 | D4: =SUMIFS(Dataset!S:S,Dataset!P:P,A4,Dataset!S:S,">0",Dataset!B:B,"Active")/1000 -> 27.251703 | E4: =SUMIFS(Dataset!Y:Y,Dataset!P:P,A4,Dataset!Y:Y,">0",Dataset!B:B,"Active")/1000 -> 209.95033 | F4: =AVERAGEIFS(Dataset!X:X,Dataset!P:P,A4,Dataset!X:X,">0",Dataset!B:B,"Active") -> 11.698659 | G4: =SUMIFS(Dataset!X:X,Dataset!P:P,A4,Dataset!X:X,">0",Dataset!B:B,"Active") -> 1918.58
A5: LPG | B5: =COUNTIFS(Dataset!P:P,A5,Dataset!B:B,"Active") -> 22 | C5: =AVERAGEIFS(Dataset!S:S,Dataset!P:P,A5,Dataset!S:S,">0",Dataset!S:S,"<>Unknown",Dataset!B:B,"Active") -> 68.097827 | D5: =SUMIFS(Dataset!S:S,Dataset!P:P,A5,Dataset!S:S,">0",Dataset!B:B,"Active")/1000 -> 1.4981522 | E5: =SUMIFS(Dataset!Y:Y,Dataset!P:P,A5,Dataset!Y:Y,">0",Dataset!B:B,"Active")/1000 -> 37.040696 | F5: =AVERAGEIFS(Dataset!X:X,Dataset!P:P,A5,Dataset!X:X,">0",Dataset!B:B,"Active") -> 64.996 | G5: =SUMIFS(Dataset!X:X,Dataset!P:P,A5,Dataset!X:X,">0",Dataset!B:B,"Active") -> 974.94
A6: Gasoline | B6: =COUNTIFS(Dataset!P:P,A6,Dataset!B:B,"Active") -> 2 | C6: =AVERAGEIFS(Dataset!S:S,Dataset!P:P,A6,Dataset!S:S,">0",Dataset!S:S,"<>Unknown",Dataset!B:B,"Active") -> 38.0307 | D6: =SUMIFS(Dataset!S:S,Dataset!P:P,A6,Dataset!S:S,">0",Dataset!B:B,"Active")/1000 -> 0.0380307 | E6: =SUMIFS(Dataset!Y:Y,Dataset!P:P,A6,Dataset!Y:Y,">0",Dataset!B:B,"Active")/1000 -> 1.9661872 | F6: =AVERAGEIFS(Dataset!X:X,Dataset!P:P,A6,Dataset!X:X,">0",Dataset!B:B,"Active") -> 28.05 | G6: =SUMIFS(Dataset!X:X,Dataset!P:P,A6,Dataset!X:X,">0",Dataset!B:B,"Active") -> 56.1
A7: Unknown | B7: =COUNTIFS(Dataset!P:P,A7,Dataset!B:B,"Active") -> 108 | C7: =AVERAGEIFS(Dataset!S:S,Dataset!P:P,A7,Dataset!S:S,">0",Dataset!S:S,"<>Unknown",Dataset!B:B,"Active") -> 287.95271 | D7: =SUMIFS(Dataset!S:S,Dataset!P:P,A7,Dataset!S:S,">0",Dataset!B:B,"Active")/1000 -> 30.235034 | E7: =SUMIFS(Dataset!Y:Y,Dataset!P:P,A7,Dataset!Y:Y,">0",Dataset!B:B,"Active")/1000 -> 215.73179 | F7: =AVERAGEIFS(Dataset!X:X,Dataset!P:P,A7,Dataset!X:X,">0",Dataset!B:B,"Active") -> 10.724247 | G7: =SUMIFS(Dataset!X:X,Dataset!P:P,A7,Dataset!X:X,">0",Dataset!B:B,"Active") -> 782.87
A9: Total | B9: =SUM(B2:B7) -> 3364 | C9: =AVERAGEIFS(Dataset!S:S,Dataset!S:S,">0",Dataset!B:B,"Active") -> 325.04079 | D9: =SUM(D2:D7) -> 1086.9364 | E9: =SUMIFS(Dataset!Y:Y,Dataset!Y:Y,">0",Dataset!B:B,"Active")/1000 -> 10023.274 | F9: =AVERAGEIFS(Dataset!X:X,Dataset!X:X,">0",Dataset!B:B,"Active") -> 13.092064 | G9: =SUM(G2:G7) -> 31211.48
D12: # of gensets with no listed capacity | F12: # of gensets not reporting hours
D13: =COUNTIFS(Dataset!S:S,"Unknown",Dataset!B:B,"Active") -> 20 | F13: =COUNTIFS(Dataset!X1:X4145,"",Dataset!B1:B4145,"Active") -> 838 | G13: =F13/3364 -> 0.2491082
D14: Additional MW if they are average sized | F14: Additional operating hours if avg.
D15: =D13*C9/1000 -> 6.5008159 | F15: =F9*F13 -> 10971.149
